{
  "Code": 204,
  "Version": 97,
  "Caokey": "SNawBD6MeebTNtSUl5UT9kS0",
  "Caokey2": "0gqy2dJNqlmY0mR4",
  "Nxflvenc": "your@menxflv@com",
  "Nxflvdec": "loveme@nxflv@com",
  "Gurl": "v.qq.com,iqiyi,youku,mgtv,pptv,sohu,le.com,1905.com,migu,fun.tv,wasu,tudou,360kan",
  "Jxpai": ".html,xyz/bei,piracy_16x9,htv009.com,973973.xyz,8old.cn,-okzy.com,okokbo.com,haozuida.com,youku.com-youku.net,163.com-163cdn.com",
  "Data": {
	"parserjson": [
	 
	 {
        "name": "8090",
		"parserType": "json",
		"webType": "iqiyi,youku,pptv,1905,migu,fun,wasu,leshi,360kan",
		"header": "",
        "url": "https://8090.gdkaman.com/jiexi20210115/api.php@referer=&ref=0&time=1611808235&type=&other=&ios=&url=",
		"enable": true
      },
      
	 {
        "name": "芒果",
		"parserType": "json",
		"webType": "mgtv",
		"header": "",
        "url": "https://plamgtvcache.ccyjjd.com/mgtv20210115%60/api.php@referer=&ref=0&time=1611813966&type=&other=&ios=&url=",
		"enable": true
      },
       {
        "name": "timer",
		"parserType": "webview",
		"webType": "qq",
		"header": "",
        "url": "https://timerd.me/static/tv.html?zwx=",
		"enable": true
      },
	 {
        "name": "诺讯",
		"parserType": "json",
		"webType": "iqiyi,qq,youku,pptv,1905,fun,wasu,leshi,migu,tudou,360kan",
		"header": "",
        "url": "https://yun.nxflv.com/Api.php@type=&wap=0&ios=0&vkey=@@@@&url=",
		"enable": true
      },

       {
        "name": "timer",
		"parserType": "webview",
		"webType": "iqiyi,youku,qq,qiyi,pptv",
		"header": "",
        "url": "https://timerd.me/static/tv.html?zwx=",
		"enable": true
      },
     
	 {
        "name": "Parwix解析",
		"parserType": "webview",
		"webType": "mgtv,1905,iqiyi,youku,qq,souhu,pptv",
		"header": "",
        "url": "https://vip.parwix.com:4433/player/?url=",
		"enable": true
      },
      	{
        "name": "m3u8解析",
		"parserType": "webview",
		"webType": "mgtv,1905.iqiyi,youku,qq,souhu,pptv",
		"header": "",
        "url": "https://jx.m3u8.tv/jiexi/?url=",
		"enable": true
      },
	 {
        "name": "久播",
		"parserType": "webview",
		"webType": "iqiyi,qq,youku,1905",
		"header": "",
        "url": "@Header:{\"Referer\": \"https://jx.jiubojx.com\"}https://vip.jiubojx.com/vip/?url=",
		"enable": true
      },

	 {
        "name": "无名",
		"parserType": "webview",
		"webType": "mgtv,pptv,iqiyi,qq,youku,1905,migu,wasu,leshi",
		"header": "",
        "url": "https://www.administratorw.com/index.php?url=",
		"enable": false
      },
   
	 {
        "name": "思古",
		"parserType": "webview",
		"webType": "iqiyi,qq,youku,sohu,pptv,1905,fun,wasu,leshi,migu,tudou",
		"header": "",
        "url": "@Header:{\"Referer\": \"https://api.sigujx.com\"}https://jx.sigujx.com/?url=",
		"enable": true
      }
    ],
    "jsapi": [
      {
        "name": "南瓜极速1",
        "url": "jk.5ebd5d.com",
        "enable": true
      },
      {
        "name": "南瓜极速2",
        "url": "jk.cf3410.com",
        "enable": false
      },
      {
        "name": "南瓜极速3",
        "url": "jk.c5714d.com",
        "enable": false
      }
    ],
    "soRule": [
    
    {
        "detailActor": "",
        "detailArea": ".area",
        "detailDesc": ".intro",
        "detailDirector": "",
        "detailImg": "",
        "detailNoteUrl": "",
        "detailRemark": "rate",
        "detailUi": "1",
        "detailYear": ".release_year",
        "discern": "",
        "enable": true,
        "enableFind": true,
        "exclude": "",
        "findActor": "",
        "findArea": "",
        "findDesc": "",
        "findDirector": "",
        "findImg": "cover_image",
        "findList": "data.data[*]",
        "findName": "name",
        "findNoteUrl": "https://kjxq.api.wlnps.com/movie/info@BODYmovie_id={$.id}",
        "findRemark": "desc",
        "findUrl": "美剧::https://kjxq.api.wlnps.com/home/movies/platform@BODYtype_id=8&page=searchPage\n英剧::https://kjxq.api.wlnps.com/home/movies/platform@BODYtype_id=14&page=searchPage\n日剧::https://kjxq.api.wlnps.com/home/movies/platform@BODYtype_id=15&page=searchPage\n电影::https://kjxq.api.wlnps.com/home/movies/platform@BODYtype_id=22&page=searchPage\n动画::https://kjxq.api.wlnps.com/home/movies/platform@BODYtype_id=24&page=searchPage\n韩剧::https://kjxq.api.wlnps.com/home/movies/platform@BODYtype_id=26&page=searchPage\n泰剧::https://kjxq.api.wlnps.com/home/movies/platform@BODYtype_id=27&page=searchPage\n西班牙剧::https://kjxq.api.wlnps.com/home/movies/platform@BODYtype_id=829&page=searchPage\n综艺::https://kjxq.api.wlnps.com/home/movies/platform@BODYtype_id=30&page=searchPage",
        "findYear": "",
        "httpUserAgent": "{\"x-client-version\": \"1.3.5\",\"x-client-time\": \"1630380037014\",\"x-device-flag\": \"43545cfb-b306-4352-a001-a591ef485590\",\"x-client-model\": \"XiaomiMI 6\",\"x-api-version\": \"1\",\"x-client-app-id\": \"com.mjxq.app\",\"x-client-type\": \"APP\",\"x-api-language\": \"Ch\",\"x-api-matching\": \"446b0fe68882823846b0d1ab0f71dae8\",\"x-client-os\": \"Android\",\"authorization\": \"e3e621a693f380cc6c203d48122fd4b9\",\"user-agent\": \"okhttp/4.9.0\",\"Content-Type\": \"application/json\"}",
        "loginText": "",
        "loginUrl": "",
        "parserType": "2",
        "parserUrl": "https://kjxq.api.wlnps.com/movie/path@BODYepisode={$.episode}&id={$.movie_id}",
        "play": ".play_path",
        "playHeader": "",
        "playList": ".episode[*]",
        "playName": "episode",
        "playUrl": "movie_id",
        "reqUrl": "",
        "searchActor": "",
        "searchArea": "area",
        "searchDesc": "",
        "searchDirector": "",
        "searchImg": "cover_image",
        "searchList": "data[*]",
        "searchName": "name",
        "searchNoteUrl": "https://kjxq.api.wlnps.com/movie/info@BODYmovie_id={$.id}",
        "searchRemark": "episode_desc",
        "searchUrl": "https://kjxq.api.wlnps.com/filter/name@BODYname=searchKey&page=1",
        "searchYear": "release_year",
        "serialNumber": 1,
        "sortName": "",
        "sortNameList": "",
        "sortUrlList": "",
        "sourceGroup": "",
        "sourceName": "外剧",
        "sourceUrl": "https://kjxq.api.wlnps.com",
        "weight": 0
    },
    {
  "detailActor": "",
  "detailArea": "",
  "detailDesc": "",
  "detailDirector": "",
  "detailImg": "class.v_pic.0@tag.img@data-src",
  "detailNoteUrl": "",
  "detailRemark": "",
  "detailUi": "1",
  "detailYear": "",
  "discern": "",
  "enable": true,
  "enableFind": true,
  "exclude": "",
  "findActor": "",
  "findArea": "",
  "findDesc": "",
  "findDirector": "",
  "findImg": "",
  "findList": "",
  "findName": "",
  "findNoteUrl": "",
  "findRemark": "",
  "findUrl": "",
  "findYear": "",
  "httpUserAgent": "Mozilla/5.0 (Linux; U; Android 8.0.0; zh-cn; Mi Note 2 Build/OPR1.170623.032) AppleWebKit/537.36 (KHTML, like Gecko) Version/4.0 Chrome/61.0.3163.128 Mobile Safari/537.36 XiaoMi/MiuiBrowser/10.1.1",
  "loginText": "",
  "loginUrl": "",
  "parserType": "4",
  "parserUrl": "",
  "play": "",
  "playHeader": "",
  "playList": "class.v_con_box@tag.li",
  "playName": "tag.em@text",
  "playUrl": "tag.a@href<js>'https://www.tv8box.com' + result</js>@js:result.replace('.html','')",
  "reqUrl": "",
  "searchActor": "",
  "searchArea": "",
  "searchDesc": "",
  "searchDirector": "",
  "searchImg": "",
  "searchList": "data[*]",
  "searchName": "vod_name",
  "searchNoteUrl": "link<js>'https://www.tv8box.com' + result</js>",
  "searchRemark": "",
  "searchUrl": "https://www.tv8box.com/index.php?g=home&m=search&a=api&sid=0&limit=10&wd=searchKey",
  "searchYear": "",
  "serialNumber": 0,
  "sortName": "",
  "sortNameList": "",
  "sortUrlList": "",
  "sourceGroup": "",
  "sourceName": "超清推荐",
  "sourceUrl": "www.tv8box.com",
  "weight": 0
},
{
  "detailActor": "",
  "detailArea": "",
  "detailDesc": "",
  "detailDirector": "",
  "detailImg": "",
  "detailNoteUrl": "",
  "detailRemark": "",
  "detailUi": "1",
  "detailYear": "",
  "discern": "",
  "enable": true,
  "enableFind": true,
  "exclude": "",
  "findActor": "",
  "findArea": "",
  "findDesc": "",
  "findDirector": "",
  "findImg": "",
  "findList": "",
  "findName": "",
  "findNoteUrl": "",
  "findRemark": "",
  "findUrl": "",
  "findYear": "",
  "httpUserAgent": "Mozilla/5.0 (Windows NT 10.0; WOW64) AppleWebKit/537.36 (KHTML, like Gecko) Chrome/70.0.3538.25 Safari/537.36 Core/1.70.3877.400 QQBrowser/10.8.4506.400",
  "loginText": "",
  "loginUrl": "",
  "parserType": "4",
  "parserUrl": "",
  "play": "",
  "playHeader": "",
  "playList": "class.stui-pannel_bd@tag.li",
  "playName": "tag.a@text",
  "playUrl": "tag.a@href<js>'https://www.7xiady.cc' + result</js>",
  "reqUrl": "",
  "searchActor": "",
  "searchArea": "",
  "searchDesc": "",
  "searchDirector": "",
  "searchImg": "tag.a@data-original",
  "searchList": "class.stui-pannel@tag.li",
  "searchName": "tag.a@title",
  "searchNoteUrl": "tag.a@href",
  "searchRemark": "tag.span.1@text",
  "searchUrl": "https://www.7xiady.cc/search/-------------/?wd=searchKey",
  "searchYear": "",
  "serialNumber": 0,
  "sortName": "",
  "sortNameList": "",
  "sortUrlList": "class.stui-pannel-box.class.stui-pannel_bd",
  "sourceGroup": "",
  "sourceName": "秋霞电影",
  "sourceUrl": "https://www.7xiady.cc",
  "weight": 0
},
    {
  "detailActor": "",
  "detailArea": "",
  "detailDesc": "",
  "detailDirector": "",
  "detailImg": "",
  "detailNoteUrl": "",
  "detailRemark": "",
  "detailUi": "1",
  "detailYear": "",
  "discern": "",
  "enable": true,
  "enableFind": true,
  "exclude": "",
  "findActor": "",
  "findArea": "",
  "findDesc": "",
  "findDirector": "",
  "findImg": "",
  "findList": "",
  "findName": "",
  "findNoteUrl": "",
  "findRemark": "",
  "findUrl": "",
  "findYear": "",
  "httpUserAgent": "",
  "loginText": "",
  "loginUrl": "",
  "parserType": "4",
  "parserUrl": "",
  "play": "",
  "playHeader": "",
  "playList": "id.player_list@tag.li",
  "playName": "tag.a@text",
  "playUrl": "tag.a@href<js>'https://auete.com' + result</js>",
  "reqUrl": "",
  "searchActor": "",
  "searchArea": "",
  "searchDesc": "",
  "searchDirector": "",
  "searchImg": "",
  "searchList": "class.card-body@tag.li",
  "searchName": "tag.a@tag.span@text",
  "searchNoteUrl": "tag.a@href",
  "searchRemark": "",
  "searchUrl": "https://auete.com/search.php?searchword=searchKey",
  "searchYear": "",
  "serialNumber": 5,
  "sortName": "",
  "sortNameList": "",
  "sortUrlList": "",
  "sourceGroup": "",
  "sourceName": "Auete",
  "sourceUrl": "https://auete.com",
  "weight": 0
},
{
  "detailActor": "",
  "detailArea": "",
  "detailDesc": "",
  "detailDirector": "",
  "detailImg": "",
  "detailNoteUrl": "",
  "detailRemark": "",
  "detailUi": "1",
  "detailYear": "",
  "discern": "",
  "enable": true,
  "enableFind": true,
  "exclude": "",
  "findActor": "",
  "findArea": "",
  "findDesc": "",
  "findDirector": "",
  "findImg": "tag.a@data-original",
  "findList": "class.myui-panel_bd@class.myui-vodlist__box",
  "findName": "tag.a@title",
  "findNoteUrl": "tag.a@href",
  "findRemark": "",
  "findUrl": "电视剧::https://fantuan.tv/vodtype/2-searchPage.html\n电影::https://fantuan.tv/vodtype/1-searchPage.html\n综艺::https://fantuan.tv/vodtype/3-searchPage.html\n动漫::https://fantuan.tv/vodtype/4-searchPage.html",
  "findYear": "",
  "httpUserAgent": "Mozilla/5.0 (Linux; U; Android 8.0.0; zh-cn; Mi Note 2 Build/OPR1.170623.032) AppleWebKit/537.36 (KHTML, like Gecko) Version/4.0 Chrome/61.0.3163.128 Mobile Safari/537.36 XiaoMi/MiuiBrowser/10.1.1",
  "loginText": "",
  "loginUrl": "",
  "parserType": "4",
  "parserUrl": "",
  "play": "",
  "playHeader": "",
  "playList": "class.tab-content.0@tag.li",
  "playName": "tag.a@text",
  "playUrl": "tag.a@href<js>'https://www.fantuan.tv' + result</js>",
  "reqUrl": "",
  "searchActor": "",
  "searchArea": "",
  "searchDesc": "",
  "searchDirector": "",
  "searchImg": "pic",
  "searchList": "list[*]",
  "searchName": "name",
  "searchNoteUrl": "id<js>'https://www.fantuan.tv/voddetail/' + result + '.html'</js>",
  "searchRemark": "",
  "searchUrl": "https://www.fantuan.tv/ajax/suggest?mid=1&wd=searchKey",
  "searchYear": "",
  "serialNumber": 6,
  "sortName": "",
  "sortNameList": "",
  "sortUrlList": "",
  "sourceGroup": "",
  "sourceName": "饭团",
  "sourceUrl": "fantuan.tv",
  "weight": 0
},
{
  "detailActor": "",
  "detailArea": "",
  "detailDesc": "",
  "detailDirector": "",
  "detailImg": "",
  "detailNoteUrl": "",
  "detailRemark": "",
  "detailUi": "1",
  "detailYear": "",
  "discern": "",
  "enable": true,
  "enableFind": true,
  "exclude": "",
  "findActor": "",
  "findArea": "",
  "findDesc": "",
  "findDirector": "",
  "findImg": "tag.a@data-original",
  "findList": "class.myui-panel-box.2@tag.li",
  "findName": "tag.h4@text",
  "findNoteUrl": "tag.a@href",
  "findRemark": "",
  "findUrl": "电影::https://www.jpysvip.net/vodtype/1-searchPage.html\n电视剧::https://www.jpysvip.net/vodtype/2-searchPage.html\n综艺::https://www.jpysvip.net/vodtype/3-searchPage.html\n动漫::https://www.jpysvip.net/vodtype/4-searchPage.html",
  "findYear": "",
  "httpUserAgent": "Mozilla/5.0 (Linux; U; Android 8.0.0; zh-cn; Mi Note 2 Build/OPR1.170623.032) AppleWebKit/537.36 (KHTML, like Gecko) Version/4.0 Chrome/61.0.3163.128 Mobile Safari/537.36 XiaoMi/MiuiBrowser/10.1.1",
  "loginText": "",
  "loginUrl": "",
  "parserType": "4",
  "parserUrl": "",
  "play": "",
  "playHeader": "",
  "playList": "id.playlist1@tag.li",
  "playName": "tag.a@text",
  "playUrl": "tag.a@href<js>'https://www.jpysvip.net' + result</js>",
  "reqUrl": "",
  "searchActor": "",
  "searchArea": "",
  "searchDesc": "",
  "searchDirector": "",
  "searchImg": "pic",
  "searchList": "list[*]",
  "searchName": "name",
  "searchNoteUrl": "id<js>'https://www.jpysvip.net/voddetail/' + result + '.html'</js>",
  "searchRemark": "",
  "searchUrl": "https://www.jpysvip.net/ajax/suggest?mid=1&wd=searchKey",
  "searchYear": "",
  "serialNumber": 7,
  "sortName": "",
  "sortNameList": "",
  "sortUrlList": "",
  "sourceGroup": "",
  "sourceName": "极品影视",
  "sourceUrl": "jpysvip.net",
  "weight": 0
},

{
  "detailActor": "",
  "detailArea": "",
  "detailDesc": "",
  "detailDirector": "",
  "detailImg": "",
  "detailNoteUrl": "",
  "detailRegex": "",
  "detailRemark": "",
  "detailUi": "1",
  "detailYear": "",
  "discern": "",
  "enable": true,
  "enableFind": false,
  "exclude": "",
  "findActor": "",
  "findArea": "",
  "findDesc": "",
  "findDirector": "",
  "findImg": "",
  "findList": "",
  "findName": "",
  "findNoteUrl": "",
  "findRemark": "",
  "findScreen": "",
  "findUrl": "",
  "findYear": "",
  "httpUserAgent": "",
  "loginText": "",
  "loginUrl": "",
  "parserType": "4",
  "parserUrl": "",
  "play": ":url\":\"(\\S*)\",\"url_next\"",
  "playHeader": "",
  "playList": "li",
  "playName": "a@text",
  "playUrl": "a@href@js:'https://cokemv.me' + result",
  "reqUrl": "",
  "searchActor": "",
  "searchArea": "",
  "searchDesc": "",
  "searchDirector": "",
  "searchImg": "pic",
  "searchList": "list[*]",
  "searchName": "name",
  "searchNoteUrl": "https://cokemv.me/voddetail/{$.id}.html",
  "searchRemark": "",
  "searchUrl": "https://cokemv.me/index.php/ajax/suggest?mid=1&wd=searchKey",
  "searchYear": "",
  "serialNumber": 3,
  "sortName": "a@text",
  "sortNameList": "class.nav-tabs@li",
  "sortUrlList": "class.myui-content__list",
  "sourceGroup": "",
  "sourceName": "COKEMV",
  "sourceUrl": "https://cokemv.me",
  "weight": 0
},


    {
  "detailActor": "",
  "detailArea": "",
  "detailDesc": "",
  "detailDirector": "",
  "detailImg": "",
  "detailNoteUrl": "",
  "detailRemark": "",
  "detailUi": "1",
  "detailYear": "",
  "discern": "",
  "enable": true,
  "enableFind": false,
  "exclude": "",
  "findActor": "",
  "findArea": "",
  "findDesc": "",
  "findDirector": "",
  "findImg": "",
  "findList": "",
  "findName": "",
  "findNoteUrl": "",
  "findRemark": "",
  "findUrl": "",
  "findYear": "",
  "httpUserAgent": "",
  "loginText": "",
  "loginUrl": "",
  "parserType": "4",
  "parserUrl": "",
  "play": "",
  "playHeader": "",
  "playList": "class.scroll-content@tag.a",
  "playName": "tag.a@text",
  "playUrl": "tag.a@href<js>'https://www.007ts.cc' + result</js>",
  "reqUrl": "",
  "searchActor": "",
  "searchArea": "",
  "searchDesc": "",
  "searchDirector": "",
  "searchImg": "class.module-item-pic@tag.img@data-src",
  "searchList": "class.module-search-item",
  "searchName": "class.video-info@tag.h3@text",
  "searchNoteUrl": "class.video-info@tag.a@href",
  "searchRemark": "",
  "searchUrl": "https://www.007ts.cc/search/-------------.html?wd=searchKey",
  "searchYear": "",
  "serialNumber": 0,
  "sortName": "",
  "sortNameList": "",
  "sortUrlList": "",
  "sourceGroup": "",
  "sourceName": "007影视",
  "sourceUrl": "https://www.007ts.cc",
  "weight": 0
},

{
  "detailActor": "class.myui-content__detail.0@class.data.2@text",
  "detailArea": "class.myui-content__detail.0@class.data.0@text##地区：(.*)年份：##$1###",
  "detailDesc": "class.sketch@text",
  "detailDirector": "class.myui-content__detail.0@class.data.3@text",
  "detailImg": "",
  "detailNoteUrl": "",
  "detailRemark": "",
  "detailUi": "1",
  "detailYear": "class.myui-content__detail.0@class.data.0@text##年份：(.*)##$1###",
  "discern": "",
  "enable": true,
  "enableFind": false,
  "exclude": "",
  "findActor": "",
  "findArea": "",
  "findDesc": "",
  "findDirector": "",
  "findImg": "",
  "findList": "",
  "findName": "",
  "findNoteUrl": "",
  "findRemark": "",
  "findUrl": "",
  "findYear": "",
  "httpUserAgent": "",
  "loginText": "",
  "loginUrl": "",
  "parserType": "4",
  "parserUrl": "",
  "play": "",
  "playHeader": "",
  "playList": "id.playlist1@tag.li",
  "playName": "tag.a.0@text",
  "playUrl": "tag.a.0@href<js>'http://vipmv.tv' + result</js>",
  "reqUrl": "",
  "searchActor": "class.detail@tag.p.1@text##主演：##",
  "searchArea": "class.detail@tag.p.2@text##地区：(.*)年份：##$1###",
  "searchDesc": "",
  "searchDirector": "class.detail@tag.p.0@text##导演：##",
  "searchImg": "class.thumb.0@tag.a.0@data-original",
  "searchList": "class.myui-panel_bd@tag.li",
  "searchName": "class.thumb@tag.a.0@title",
  "searchNoteUrl": "class.detail.0@class.title.0@tag.a.0@href",
  "searchRemark": "tag.a.0@class.pic-text@text",
  "searchUrl": "http://vipmv.tv/index.php/vod/search/wd/searchKey.html",
  "searchYear": "class.detail@tag.p.2@text##年份：(.*)##$1###",
  "serialNumber": 11,
  "sortName": "",
  "sortNameList": "",
  "sortUrlList": "",
  "sourceGroup": "",
  "sourceName": "追剧达人",
  "sourceUrl": "http://vipmv.tv",
  "weight": 0
},
{
  "detailActor": "class.data@class.act@text##主演：##",
  "detailArea": "class.data@class.yac@text##\\((.*)\\)##$1###",
  "detailDesc": "class.tbox_js@text## ##",
  "detailDirector": "class.data@class.dir@text##导演：##",
  "detailImg": "",
  "detailNoteUrl": "",
  "detailRemark": "",
  "detailUi": "1",
  "detailYear": "class.data@class.yac@text##([^-]+)##$1###",
  "discern": "",
  "enable": true,
  "enableFind": true,
  "exclude": "",
  "findActor": "",
  "findArea": "",
  "findDesc": "",
  "findDirector": "",
  "findImg": "",
  "findList": "",
  "findName": "",
  "findNoteUrl": "",
  "findRemark": "",
  "findUrl": "电影::http://www.yc2050.com/type/1/searchPage.html&&电视剧::http://www.yc2050.com/type/2/searchPage.html&&动漫::http://www.yc2050.com/type/7/searchPage.html&&综艺::http://www.yc2050.com/type/4/searchPage.html&&恐怖::http://www.yc2050.com/type/9/searchPage.html",
  "findYear": "",
  "httpUserAgent": "",
  "loginText": "",
  "loginUrl": "",
  "parserType": "4",
  "parserUrl": "",
  "play": "",
  "playHeader": "",
  "playList": "tag.a",
  "playName": "tag.a@text",
  "playUrl": "tag.a@href<js>'https://www.wydy8.com' + result</js>",
  "reqUrl": "",
  "searchActor": "",
  "searchArea": "",
  "searchDesc": "",
  "searchDirector": "",
  "searchImg": "tag.img@src",
  "searchList": "class.result-item",
  "searchName": "tag.a@title",
  "searchNoteUrl": "tag.a.0@href",
  "searchRemark": "tag.a@tag.span@text",
  "searchUrl": "https://www.wydy8.com/index.php?m=vod-search-wd-searchKey",
  "searchYear": "",
  "serialNumber": 32,
  "sortName": "",
  "sortNameList": "",
  "sortUrlList": "class.panel",
  "sourceGroup": "",
  "sourceName": "万影网",
  "sourceUrl": "http://www.yc2050.com",
  "weight": 0
},
{
  "detailActor": "class.data.1@text",
  "detailArea": "class.data.0@tag.a.1@text",
  "detailDesc": "class.data.4@text",
  "detailDirector": "class.data.2@text",
  "detailImg": "",
  "detailNoteUrl": "",
  "detailRemark": "class.myui-content__detail@tag.h1@tag.font@text",
  "detailUi": "1",
  "detailYear": "class.data@tag.a.2@text",
  "discern": "",
  "enable": true,
  "enableFind": true,
  "exclude": "gfd9fkd.mp4",
  "findActor": "",
  "findArea": "",
  "findDesc": "",
  "findDirector": "",
  "findImg": "",
  "findList": "",
  "findName": "",
  "findNoteUrl": "",
  "findRemark": "",
  "findUrl": "",
  "findYear": "",
  "httpUserAgent": "Mozilla/5.0 (Windows NT 6.1; rv,2.0.1) Gecko/20100101 Firefox/4.0.1",
  "loginText": "",
  "loginUrl": "",
  "parserType": "4",
  "parserUrl": "",
  "play": "",
  "playHeader": "",
  "playList": "class.myui-panel_bd.2@tag.li",
  "playName": "tag.a@text",
  "playUrl": "tag.a@href@js:result.replace('/vodplay/','https://nfxhd.com/vodplay/')",
  "reqUrl": "",
  "searchActor": "class.detail@tag.p.1",
  "searchArea": "tag.li.2@text",
  "searchDesc": "",
  "searchDirector": "class.detail@tag.p.0",
  "searchImg": "class.thumb@tag.a.0@data-original",
  "searchList": "class.myui-panel_bd@tag.li",
  "searchName": "class.detail@tag.a.0@text",
  "searchNoteUrl": "tag.a.0@href",
  "searchRemark": "",
  "searchUrl": "https://nfxhd.com/vodsearch/-------------/?wd=searchKey",
  "searchYear": "",
  "serialNumber": 13,
  "sortName": "",
  "sortNameList": "",
  "sortUrlList": "",
  "sourceGroup": "",
  "sourceName": "奈飞星",
  "sourceUrl": "https://nfxhd.com",
  "weight": 0
},
{
  "detailActor": "class.data.1@text",
  "detailArea": "class.data.0@tag.a.1@text",
  "detailDesc": "class.data.4@text",
  "detailDirector": "class.data.2@text",
  "detailImg": "",
  "detailNoteUrl": "",
  "detailRemark": "class.myui-content__detail@tag.h1@tag.font@text",
  "detailUi": "1",
  "detailYear": "class.data@tag.a.2@text",
  "discern": "",
  "enable": true,
  "enableFind": true,
  "exclude": "",
  "findActor": "",
  "findArea": "",
  "findDesc": "",
  "findDirector": "",
  "findImg": "",
  "findList": "",
  "findName": "",
  "findNoteUrl": "",
  "findRemark": "",
  "findUrl": "",
  "findYear": "",
  "httpUserAgent": "Mozilla/5.0 (Linux; U; Android 8.0.0; zh-cn; Mi Note 2 Build/OPR1.170623.032) AppleWebKit/537.36 (KHTML, like Gecko) Version/4.0 Chrome/61.0.3163.128 Mobile Safari/537.36 XiaoMi/MiuiBrowser/10.1.1",
  "loginText": "",
  "loginUrl": "",
  "parserType": "4",
  "parserUrl": "",
  "play": "",
  "playHeader": "",
  "playList": "class.myui-panel_bd.2@tag.li",
  "playName": "tag.a@text",
  "playUrl": "tag.a@href<js>'http://www.tvyb02.com' + result</js>",
  "reqUrl": "",
  "searchActor": "class.detail@tag.p.1",
  "searchArea": "tag.li.2@text",
  "searchDesc": "",
  "searchDirector": "class.detail@tag.p.0",
  "searchImg": "class.thumb@tag.a.0@data-original",
  "searchList": "class.myui-panel_bd.0@tag.li",
  "searchName": "class.detail@tag.a.0@text",
  "searchNoteUrl": "tag.a.0@href",
  "searchRemark": "class.thumb@tag.a.0@tag.span.2@text",
  "searchUrl": "http://www.tvyb02.com/vod/search/wd/searchKey.html",
  "searchYear": "",
  "serialNumber": 51,
  "sortName": "",
  "sortNameList": "",
  "sortUrlList": "",
  "sourceGroup": "",
  "sourceName": "tvb云播",
  "sourceUrl": "http://www.tvyb02.com",
  "weight": 0
},
{
  "detailActor": "",
  "detailArea": "",
  "detailDesc": "",
  "detailDirector": "",
  "detailImg": "",
  "detailNoteUrl": "",
  "detailRemark": "",
  "detailUi": "1",
  "detailYear": "",
  "discern": "",
  "enable": true,
  "enableFind": true,
  "exclude": "",
  "findActor": "",
  "findArea": "",
  "findDesc": "",
  "findDirector": "",
  "findImg": "",
  "findList": "",
  "findName": "",
  "findNoteUrl": "",
  "findRemark": "",
  "findUrl": "",
  "findYear": "",
  "httpUserAgent": "",
  "loginText": "",
  "loginUrl": "",
  "parserType": "4",
  "parserUrl": "",
  "play": "",
  "playHeader": "",
  "playList": "class.list-unstyled-play@tag.li",
  "playName": "tag.a@text",
  "playUrl": "tag.a@href<js>'https://3edy.com' + result</js>",
  "reqUrl": "",
  "searchActor": "",
  "searchArea": "",
  "searchDesc": "",
  "searchDirector": "",
  "searchImg": "tag.img@data-original",
  "searchList": "class.list-unstyled@tag.li",
  "searchName": "tag.h4@text",
  "searchNoteUrl": "tag.a@href",
  "searchRemark": "class.label@tag.em@text",
  "searchUrl": "https://3edy.com/vodsearch/-------------.html?wd=searchKey",
  "searchYear": "",
  "serialNumber": 0,
  "sortName": "",
  "sortNameList": "",
  "sortUrlList": "",
  "sourceGroup": "",
  "sourceName": "飘花电影",
  "sourceUrl": "www.3edy.com",
  "weight": 0
},
{
  "detailActor": "class.data.1@text",
  "detailArea": "class.data.0@tag.a.1@text",
  "detailDesc": "class.data.4@text",
  "detailDirector": "class.data.2@text",
  "detailImg": "",
  "detailNoteUrl": "",
  "detailRemark": "class.myui-content__detail@tag.h1@tag.font@text",
  "detailUi": "1",
  "detailYear": "class.data@tag.a.2@text",
  "discern": "",
  "enable": true,
  "enableFind": true,
  "exclude": "",
  "findActor": "",
  "findArea": "",
  "findDesc": "",
  "findDirector": "",
  "findImg": "",
  "findList": "",
  "findName": "",
  "findNoteUrl": "",
  "findRemark": "",
  "findUrl": "",
  "findYear": "",
  "httpUserAgent": "Mozilla/5.0 (Linux; U; Android 8.0.0; zh-cn; Mi Note 2 Build/OPR1.170623.032) AppleWebKit/537.36 (KHTML, like Gecko) Version/4.0 Chrome/61.0.3163.128 Mobile Safari/537.36 XiaoMi/MiuiBrowser/10.1.1",
  "loginText": "",
  "loginUrl": "",
  "parserType": "4",
  "parserUrl": "",
  "play": "",
  "playHeader": "",
  "playList": "class.tab-content.0@tag.li",
  "playName": "tag.a@title",
  "playUrl": "tag.a@href@js:result.replace('/play/','http://www.n5m5.com/play/')",
  "reqUrl": "",
  "searchActor": "class.detail@tag.p.1@text@js:result.replace('主演：','')",
  "searchArea": "tag.li.2@text",
  "searchDesc": "",
  "searchDirector": "class.detail@tag.p.0@text@js:result.replace('导演：','')",
  "searchImg": "class.thumb@tag.a.0@data-original",
  "searchList": "class.stui-pannel_bd@tag.li",
  "searchName": "class.detail@tag.a.0@text",
  "searchNoteUrl": "tag.a.0@href",
  "searchRemark": "class.thumb@tag.a.0@tag.span.0@text",
  "searchUrl": "http://n5m5.com/search.php@searchword=searchKey",
  "searchYear": "",
  "serialNumber": 39,
  "sortName": "",
  "sortNameList": "",
  "sortUrlList": "",
  "sourceGroup": "",
  "sourceName": "酷客影视",
  "sourceUrl": "https://www.n5m5.com",
  "weight": 0
},
{
  "detailActor": "class.data.1@text",
  "detailArea": "class.data.0@tag.a.1@text",
  "detailDesc": "class.data.4@text",
  "detailDirector": "class.data.2@text",
  "detailImg": "",
  "detailNoteUrl": "",
  "detailRemark": "class.myui-content__detail@tag.h1@tag.font@text",
  "detailUi": "1",
  "detailYear": "class.data@tag.a.2@text",
  "discern": "",
  "enable": true,
  "enableFind": true,
  "exclude": "",
  "findActor": "",
  "findArea": "",
  "findDesc": "",
  "findDirector": "",
  "findImg": "",
  "findList": "",
  "findName": "",
  "findNoteUrl": "",
  "findRemark": "",
  "findUrl": "",
  "findYear": "",
  "httpUserAgent": "Mozilla/5.0 (Windows NT 6.1; rv,2.0.1) Gecko/20100101 Firefox/4.0.1",
  "loginText": "",
  "loginUrl": "",
  "parserType": "4",
  "parserUrl": "",
  "play": "",
  "playHeader": "",
  "playList": "class.stui-pannel_bd.0@tag.li",
  "playName": "tag.a@text",
  "playUrl": "tag.a@href@js:result.replace('/vodplay/','http://yeyemi.com/vodplay/')",
  "reqUrl": "",
  "searchActor": "class.detail@tag.p.1@text",
  "searchArea": "",
  "searchDesc": "",
  "searchDirector": "class.detail@tag.p.0@text",
  "searchImg": "class.thumb@tag.a.0@data-original",
  "searchList": "class.stui-pannel_bd@tag.li",
  "searchName": "class.detail@tag.a.0@text",
  "searchNoteUrl": "tag.a.0@href",
  "searchRemark": "class.thumb@tag.a.0@tag.span.2@text",
  "searchUrl": "http://yeyemi.com/vodsearch/-------------/?wd=searchKey",
  "searchYear": "",
  "serialNumber": 13,
  "sortName": "",
  "sortNameList": "",
  "sortUrlList": "",
  "sourceGroup": "",
  "sourceName": "夜夜迷",
  "sourceUrl": "http://yeyemi.com",
  "weight": 0
},


{
  "detailActor": "",
  "detailArea": "",
  "detailDesc": "tag.meta.2@content",
  "detailDirector": "",
  "detailImg": "",
  "detailNoteUrl": "",
  "detailRemark": "",
  "detailUi": "1",
  "detailYear": "",
  "discern": "",
  "enable": true,
  "enableFind": false,
  "exclude": "",
  "findActor": "",
  "findArea": "",
  "findDesc": "",
  "findDirector": "",
  "findImg": "",
  "findList": "",
  "findName": "",
  "findNoteUrl": "",
  "findRemark": "",
  "findUrl": "",
  "findYear": "",
  "httpUserAgent": "Mozilla/5.0 (Linux; Android 10; VOG-AL00) AppleWebKit/537.36 (KHTML, like Gecko) Chrome/78.0.3904.108 Mobile Safari/537.36",
  "loginText": "",
  "loginUrl": "",
  "parserType": "4",
  "parserUrl": "",
  "play": "",
  "playHeader": "",
  "playList": "//li",
  "playName": "//a/text()",
  "playUrl": "//a/@href<js>'http://m.msong.net' + result</js>",
  "reqUrl": "jx.qinian.cc",
  "searchActor": "class.sDes@tag.em.1@text",
  "searchArea": "class.sDes.2@text##类型：##",
  "searchDesc": "",
  "searchDirector": "",
  "searchImg": "tag.a@tag.img@data-src",
  "searchList": "id.data_list@tag.li",
  "searchName": "class.sTit@text",
  "searchNoteUrl": "tag.a@href",
  "searchRemark": "class.sDes.1@text##状态：##",
  "searchUrl": "http://m.msong.net/tv-search-wd-searchKey.html",
  "searchYear": "",
  "serialNumber": 33,
  "sortName": "//text()",
  "sortNameList": "//ul[@id='yunbo_t_ul']/li",
  "sortUrlList": "//div[starts-with(@id,'yunbo_tab')]/ul",
  "sourceGroup": "",
  "sourceName": "泡泡影视",
  "sourceUrl": "http://m.msong.net",
  "weight": 0
},
{
  "detailActor": "class.data.1@text",
  "detailArea": "class.data.0@tag.a.1@text",
  "detailDesc": "class.data.4@text",
  "detailDirector": "class.data.2@text",
  "detailImg": "",
  "detailNoteUrl": "",
  "detailRemark": "class.myui-content__detail@tag.h1@tag.font@text",
  "detailUi": "1",
  "detailYear": "class.data@tag.a.2@text",
  "discern": "",
  "enable": true,
  "enableFind": true,
  "exclude": "",
  "findActor": "",
  "findArea": "",
  "findDesc": "",
  "findDirector": "",
  "findImg": "",
  "findList": "",
  "findName": "",
  "findNoteUrl": "",
  "findRemark": "",
  "findUrl": "",
  "findYear": "",
  "httpUserAgent": "Mozilla/5.0 (Windows NT 6.1; rv,2.0.1) Gecko/20100101 Firefox/4.0.1",
  "loginText": "",
  "loginUrl": "",
  "parserType": "4",
  "parserUrl": "",
  "play": "",
  "playHeader": "",
  "playList": "class.tab-content.0@tag.li",
  "playName": "tag.a@title",
  "playUrl": "tag.a@href@js:result.replace('/vodplay/','https://nkdyw.cn/vodplay/')",
  "reqUrl": "",
  "searchActor": "class.detail@tag.p.1",
  "searchArea": "tag.li.2@text",
  "searchDesc": "",
  "searchDirector": "class.detail@tag.p.0",
  "searchImg": "class.thumb@tag.a.0@data-original",
  "searchList": "class.myui-panel_bd@tag.li",
  "searchName": "class.detail@tag.a.0@text",
  "searchNoteUrl": "tag.a.0@href",
  "searchRemark": "class.thumb@tag.a.0@tag.span.2@text",
  "searchUrl": "https://nkdyw.cn/nk/-------------/?wd=searchKey",
  "searchYear": "",
  "serialNumber": 41,
  "sortName": "",
  "sortNameList": "",
  "sortUrlList": "",
  "sourceGroup": "",
  "sourceName": "南柯电影网",
  "sourceUrl": "https://nkdyw.cn",
  "weight": 0
},
{
  "detailActor": "class.albumDetailMedia@tag.li.2@text",
  "detailArea": "",
  "detailDesc": "class.movie_story3@text",
  "detailDirector": "class.albumDetailMedia@tag.li.1@text",
  "detailImg": "",
  "detailNoteUrl": "",
  "detailRemark": "class.albumDetailMedia@tag.li.3@text",
  "detailUi": "1",
  "detailYear": "class.albumDetailMedia@tag.li.0@text",
  "discern": "",
  "enable": true,
  "enableFind": true,
  "exclude": "gfd9fkd.mp4",
  "findActor": "",
  "findArea": "",
  "findDesc": "",
  "findDirector": "",
  "findImg": "",
  "findList": "",
  "findName": "",
  "findNoteUrl": "",
  "findRemark": "",
  "findUrl": "",
  "findYear": "",
  "httpUserAgent": "",
  "loginText": "",
  "loginUrl": "",
  "parserType": "4",
  "parserUrl": "",
  "play": "",
  "playHeader": "",
  "playList": "id.vlink_1@tag.li",
  "playName": "tag.a@title",
  "playUrl": "tag.a@href@js:result.replace('/index.php','https://v.kyikan.com/index.php')",
  "reqUrl": "",
  "searchActor": "tag.p.1@text",
  "searchArea": "",
  "searchDesc": "",
  "searchDirector": "",
  "searchImg": "tag.a@tag.img@data-original",
  "searchList": "class.index-area@tag.li",
  "searchName": "tag.a@title",
  "searchNoteUrl": "tag.a@href@js:result.replace('/vodhtml','https://v.kyikan.com/vodhtml')",
  "searchRemark": "tag.p.4@text",
  "searchUrl": "https://v.kyikan.com/index.php?m=vod-search-pg-1-wd-searchKey",
  "searchYear": "",
  "serialNumber": 9,
  "sortName": "",
  "sortNameList": "",
  "sortUrlList": "",
  "sourceGroup": "",
  "sourceName": "看一看影视",
  "sourceUrl": "https://v.kyikan.com",
  "weight": 0
},
    {
  "detailActor": "",
  "detailArea": "",
  "detailDesc": "",
  "detailDirector": "",
  "detailImg": "",
  "detailNoteUrl": "",
  "detailRemark": "",
  "detailUi": "1",
  "detailYear": "",
  "discern": "",
  "enable": true,
  "enableFind": false,
  "exclude": "",
  "findActor": "",
  "findArea": "",
  "findDesc": "",
  "findDirector": "",
  "findImg": "",
  "findList": "",
  "findName": "",
  "findNoteUrl": "",
  "findRemark": "",
  "findUrl": "",
  "findYear": "",
  "httpUserAgent": "Mozilla/5.0 (Linux; U; Android 8.0.0; zh-cn; Mi Note 2 Build/OPR1.170623.032) AppleWebKit/537.36 (KHTML, like Gecko) Version/4.0 Chrome/61.0.3163.128 Mobile Safari/537.36 XiaoMi/MiuiBrowser/10.1.1",
  "loginText": "",
  "loginUrl": "",
  "parserType": "4",
  "parserUrl": "",
  "play": "",
  "playHeader": "",
  "playList": "",
  "playName": "",
  "playUrl": "data.vod_play_list[0].url&&data.vod_play_list[0].from",
  "reqUrl": "",
  "searchActor": "vod_actor",
  "searchArea": "vod_area",
  "searchDesc": "vod_content@js:java.Fhtml(result)",
  "searchDirector": "vod_director",
  "searchImg": "vod_pic",
  "searchList": "data.list[*]",
  "searchName": "vod_name",
  "searchNoteUrl": "http://app.siguyy.com/mogai_api.php/v1.vod/detail?vod_id={$.vod_id}",
  "searchRemark": "vod_remarks",
  "searchUrl": "http://app.siguyy.com/mogai_api.php/v1.vod?page1&limit=10=&wd=searchKey",
  "searchYear": "vod_year",
  "serialNumber": 27,
  "sortName": "",
  "sortNameList": "",
  "sortUrlList": "",
  "sourceGroup": "",
  "sourceName": "思古影视",
  "sourceUrl": "http://www.siguyy.com",
  "weight": 0
},
/*
{
  "detailActor": "",
  "detailArea": "",
  "detailDesc": "",
  "detailDirector": "",
  "detailImg": "",
  "detailNoteUrl": "",
  "detailRemark": "",
  "detailUi": "1",
  "detailYear": "",
  "discern": "",
  "enable": true,
  "enableFind": false,
  "exclude": "",
  "findActor": "",
  "findArea": "",
  "findDesc": "",
  "findDirector": "",
  "findImg": "",
  "findList": "",
  "findName": "",
  "findNoteUrl": "",
  "findRemark": "",
  "findUrl": "",
  "findYear": "",
  "httpUserAgent": "Mozilla/5.0 (Linux; U; Android 8.0.0; zh-cn; Mi Note 2 Build/OPR1.170623.032) AppleWebKit/537.36 (KHTML, like Gecko) Version/4.0 Chrome/61.0.3163.128 Mobile Safari/537.36 XiaoMi/MiuiBrowser/10.1.1",
  "loginText": "",
  "loginUrl": "",
  "parserType": "3",
  "parserUrl": "",
  "play": "",
  "playHeader": "",
  "playList": "",
  "playName": "",
  "playUrl": "data.vod_play_list[0].url&&data.vod_play_list[0].from",
  "reqUrl": "",
  "searchActor": "vod_actor",
  "searchArea": "vod_area",
  "searchDesc": "vod_content@js:java.Fhtml(result)",
  "searchDirector": "vod_director",
  "searchImg": "vod_pic",
  "searchList": "data.list[*]",
  "searchName": "vod_name",
  "searchNoteUrl": "http://myapp.maguays.cc/mogai_api.php/v1.vod/detail?vod_id={$.vod_id}",
  "searchRemark": "vod_remarks",
  "searchUrl": "http://myapp.maguays.cc/mogai_api.php/v1.vod?page1&limit=10=&wd=searchKey",
  "searchYear": "vod_year",
  "serialNumber": 27,
  "sortName": "",
  "sortNameList": "",
  "sortUrlList": "",
  "sourceGroup": "",
  "sourceName": "麻瓜影视",
  "sourceUrl": "http://www.siguyy.com",
  "weight": 0
},
*/
    {
  "detailActor": "",
  "detailArea": "",
  "detailDesc": "",
  "detailDirector": "",
  "detailImg": "",
  "detailNoteUrl": "",
  "detailRemark": "",
  "detailUi": "1",
  "detailYear": "",
  "discern": "",
  "enable": true,
  "enableFind": false,
  "exclude": "",
  "findActor": "",
  "findArea": "",
  "findDesc": "",
  "findDirector": "",
  "findImg": "",
  "findList": "",
  "findName": "",
  "findNoteUrl": "",
  "findRemark": "",
  "findUrl": "",
  "findYear": "",
  "httpUserAgent": "Mozilla/5.0 (Linux; U; Android 8.0.0; zh-cn; Mi Note 2 Build/OPR1.170623.032) AppleWebKit/537.36 (KHTML, like Gecko) Version/4.0 Chrome/61.0.3163.128 Mobile Safari/537.36 XiaoMi/MiuiBrowser/10.1.1",
  "loginText": "",
  "loginUrl": "",
  "parserType": "4",
  "parserUrl": "",
  "play": "",
  "playHeader": "",
  "playList": "",
  "playName": "",
  "playUrl": "list[0].vod_play_url&&list[0].vod_play_from",
  "reqUrl": "",
  "searchActor": "vod_actor",
  "searchArea": "vod_area",
  "searchDesc": "vod_content@js:java.Fhtml(result)",
  "searchDirector": "vod_director",
  "searchImg": "vod_pic",
  "searchList": "list[*]",
  "searchName": "vod_name",
  "searchNoteUrl": "http://db.taijuwang.cc/api.php/provide/vod/?ac=videolist&ids={$.vod_id}",
  "searchRemark": "vod_remarks",
  "searchUrl": "http://db.taijuwang.cc/api.php/provide/vod/?ac=videolist&wd=searchKey",
  "searchYear": "vod_year",
  "serialNumber": 15,
  "sortName": "",
  "sortNameList": "",
  "sortUrlList": "",
  "sourceGroup": "",
  "sourceName": "蓝光资源",
  "sourceUrl": "http://db.taijuwang.cc",
  "weight": 0
},
 {
  "detailActor": "",
  "detailArea": "",
  "detailDesc": "",
  "detailDirector": "",
  "detailImg": "",
  "detailNoteUrl": "",
  "detailRemark": "",
  "detailUi": "1",
  "detailYear": "",
  "discern": "",
  "enable": true,
  "enableFind": false,
  "exclude": "",
  "findActor": "",
  "findArea": "",
  "findDesc": "",
  "findDirector": "",
  "findImg": "",
  "findList": "",
  "findName": "",
  "findNoteUrl": "",
  "findRemark": "",
  "findUrl": "",
  "findYear": "",
  "httpUserAgent": "Mozilla/5.0 (Linux; U; Android 8.0.0; zh-cn; Mi Note 2 Build/OPR1.170623.032) AppleWebKit/537.36 (KHTML, like Gecko) Version/4.0 Chrome/61.0.3163.128 Mobile Safari/537.36 XiaoMi/MiuiBrowser/10.1.1",
  "loginText": "",
  "loginUrl": "",
  "parserType": "4",
  "parserUrl": "",
  "play": "",
  "playHeader": "",
  "playList": "",
  "playName": "",
  "playUrl": "list[0].vod_play_url&&list[0].vod_play_from",
  "reqUrl": "",
  "searchActor": "vod_actor",
  "searchArea": "vod_area",
  "searchDesc": "vod_content@js:java.Fhtml(result)",
  "searchDirector": "vod_director",
  "searchImg": "vod_pic",
  "searchList": "list[*]",
  "searchName": "vod_name",
  "searchNoteUrl": "http://xp.taijuwang.cc/api.php/provide/vod/?ac=videolist&ids={$.vod_id}",
  "searchRemark": "vod_remarks",
  "searchUrl": "http://xp.taijuwang.cc/api.php/provide/vod/?ac=videolist&wd=searchKey",
  "searchYear": "vod_year",
  "serialNumber": 15,
  "sortName": "",
  "sortNameList": "",
  "sortUrlList": "",
  "sourceGroup": "",
  "sourceName": "小鹏奇啪行",
  "sourceUrl": "http://xp.taijuwang.cc",
  "weight": 0
},

{
  "detailActor": "",
  "detailArea": "",
  "detailDesc": "class.movie_story3@text",
  "detailDirector": "",
  "detailImg": "",
  "detailNoteUrl": "",
  "detailRemark": "",
  "detailUi": "1",
  "detailYear": "",
  "discern": "",
  "enable": true,
  "enableFind": true,
  "exclude": "",
  "findActor": "",
  "findArea": "",
  "findDesc": "",
  "findDirector": "",
  "findImg": "tag.img@src",
  "findList": "class.lpic@tag.li",
  "findName": "tag.h2@tag.a",
  "findNoteUrl": "",
  "findRemark": "",
  "findUrl": "新番::http://www.yhdm.so/2021/",
  "findYear": "",
  "httpUserAgent": "",
  "loginText": "",
  "loginUrl": "",
  "parserType": "4",
  "parserUrl": "",
  "play": "",
  "playHeader": "",
  "playList": "class.movurl@tag.li",
  "playName": "tag.a@text",
  "playUrl": "tag.a@href@js:result.replace('/v/','http://www.yhdm.so/v/')",
  "reqUrl": "",
  "searchActor": "tag.span.9@class.cell_imform_value@text",
  "searchArea": "tag.span.7@class.cell_imform_value@text",
  "searchDesc": "tag.li@tag.p@text",
  "searchDirector": "tag.span.5@class.cell_imform_value@text",
  "searchImg": "tag.a@img@src",
  "searchList": "class.lpic@tag.li",
  "searchName": "tag.h2@tag.a@title",
  "searchNoteUrl": "tag.a.0@href",
  "searchRemark": "tag.a.0@style.newname@text",
  "searchUrl": "http://www.yhdm.so/search/searchKey/",
  "searchYear": "tag.span@class.cell_imform_kv@text",
  "serialNumber": 16,
  "sortName": "",
  "sortNameList": "",
  "sortUrlList": "",
  "sourceGroup": "",
  "sourceName": "樱花动漫",
  "sourceUrl": "http://www.yhdm.so",
  "weight": 0
},
    {
  "detailActor": "",
  "detailArea": "",
  "detailDesc": "",
  "detailDirector": "",
  "detailImg": "",
  "detailNoteUrl": "",
  "detailRemark": "",
  "detailUi": "1",
  "detailYear": "",
  "discern": "",
  "enable": true,
  "enableFind": false,
  "exclude": "",
  "findActor": "",
  "findArea": "",
  "findDesc": "",
  "findDirector": "",
  "findImg": "",
  "findList": "",
  "findName": "",
  "findNoteUrl": "",
  "findRemark": "",
  "findUrl": "",
  "findYear": "",
  "httpUserAgent": "",
  "loginText": "",
  "loginUrl": "",
  "parserType": "3",
  "parserUrl": "",
  "play": "",
  "playHeader": "",
  "playList": "",
  "playName": "",
  "playUrl": "list[0].vod_play_url",
  "reqUrl": "",
  "searchActor": "vod_actor",
  "searchArea": "vod_area",
  "searchDesc": "vod_content@js:java.Fhtml(result)",
  "searchDirector": "vod_director",
  "searchImg": "vod_pic",
  "searchList": "list[*]",
  "searchName": "vod_name",
  "searchNoteUrl": "http://v.paimaijie.com/api.php/provide/vod/?ac=videolist&ids={$.vod_id}",
  "searchRemark": "vod_remarks",
  "searchUrl": "http://v.paimaijie.com/api.php/provide/vod/?ac=videolist&wd=searchKey",
  "searchYear": "vod_year",
  "serialNumber": 0,
  "sortName": "",
  "sortNameList": "",
  "sortUrlList": "",
  "sourceGroup": "",
  "sourceName": "5A资源",
  "sourceUrl": "http://v.paimaijie.com",
  "weight": 1
},

{
  "detailActor": "",
  "detailArea": "",
  "detailDesc": "",
  "detailDirector": "",
  "detailImg": "",
  "detailNoteUrl": "",
  "detailRemark": "",
  "detailUi": "1",
  "detailYear": "",
  "discern": "",
  "enable": true,
  "enableFind": false,
  "exclude": "",
  "findActor": "",
  "findArea": "",
  "findDesc": "",
  "findDirector": "",
  "findImg": "",
  "findList": "",
  "findName": "",
  "findNoteUrl": "",
  "findRemark": "",
  "findUrl": "",
  "findYear": "",
  "httpUserAgent": "",
  "loginText": "",
  "loginUrl": "",
  "parserType": "3",
  "parserUrl": "",
  "play": "",
  "playHeader": "",
  "playList": "",
  "playName": "",
  "playUrl": "list[0].vod_play_url",
  "reqUrl": "",
  "searchActor": "vod_actor",
  "searchArea": "vod_area",
  "searchDesc": "vod_content@js:java.Fhtml(result)",
  "searchDirector": "vod_director",
  "searchImg": "vod_pic",
  "searchList": "list[*]",
  "searchName": "vod_name",
  "searchNoteUrl": "http://api.hszbj.net/api.php/provide/vod/?ac=videolist&ids={$.vod_id}",
  "searchRemark": "vod_remarks",
  "searchUrl": "http://api.hszbj.net/api.php/provide/vod/?ac=videolist&wd=searchKey",
  "searchYear": "vod_year",
  "serialNumber": 0,
  "sortName": "",
  "sortNameList": "",
  "sortUrlList": "",
  "sourceGroup": "",
  "sourceName": "超清资源",
  "sourceUrl": "http://api.hszbj.net",
  "weight": 1
},
{
  "detailActor": "",
  "detailArea": "vod_area",
  "detailDesc": "",
  "detailDirector": "",
  "detailImg": "vod_pic",
  "detailNoteUrl": "",
  "detailRemark": "",
  "detailUi": "1",
  "detailYear": "vod_year",
  "discern": "",
  "enable": true,
  "enableFind": false,
  "exclude": "",
  "findActor": "",
  "findArea": "",
  "findDesc": "",
  "findDirector": "",
  "findImg": "",
  "findList": "",
  "findName": "",
  "findNoteUrl": "",
  "findRemark": "",
  "findUrl": "",
  "findYear": "",
  "httpUserAgent": "",
  "loginText": "",
  "loginUrl": "",
  "parserType": "4",
  "parserUrl": "",
  "play": "",
  "playHeader": "",
  "playList": "tag.li",
  "playName": "tag.a@text",
  "playUrl": "tag.a@href",
  "reqUrl": "",
  "searchActor": "",
  "searchArea": "",
  "searchDesc": "",
  "searchDirector": "",
  "searchImg": "class.searchlist_img@tag.a@data-original",
  "searchList": "class.pannel@tag.li",
  "searchName": "tag.a@title",
  "searchNoteUrl": "tag.a@href",
  "searchRemark": "tag.span.1@text",
  "searchUrl": "http://aidi.tv/vsearch/-------------.html?wd=searchKey",
  "searchYear": "",
  "serialNumber": 8,
  "sortName": "",
  "sortNameList": "",
  "sortUrlList": "id.playlistbox.class.content_playlist",
  "sourceGroup": "",
  "sourceName": "爱迪影视",
  "sourceUrl": "http://aidi.tv",
  "weight": 0
},
{
  "detailActor": "class.data.1@text",
  "detailArea": "class.data.0@tag.a.1@text",
  "detailDesc": "class.data.4@text",
  "detailDirector": "class.data.2@text",
  "detailImg": "",
  "detailNoteUrl": "",
  "detailRemark": "class.myui-content__detail@tag.h1@tag.font@text",
  "detailUi": "1",
  "detailYear": "class.data@tag.a.2@text",
  "discern": "",
  "enable": true,
  "enableFind": true,
  "exclude": "",
  "findActor": "",
  "findArea": "",
  "findDesc": "",
  "findDirector": "",
  "findImg": "",
  "findList": "",
  "findName": "",
  "findNoteUrl": "",
  "findRemark": "",
  "findUrl": "",
  "findYear": "",
  "httpUserAgent": "Mozilla/5.0 (Linux; U; Android 10; zh-CN; Mi 10 Build/QKQ1.191117.002) AppleWebKit/537.36 (KHTML, like Gecko) Version/4.0 Chrome/78.0.3904.108 Quark/5.0.6.179 Mobile Safari/537.36",
  "loginText": "",
  "loginUrl": "",
  "parserType": "4",
  "parserUrl": "",
  "play": "",
  "playHeader": "",
  "playList": "class.top-list-ji-fl@tag.li",
  "playName": "tag.a@text",
  "playUrl": "tag.a@href@js:result.replace('/vod-play/','https://www.91kanju.com/vod-play/')",
  "reqUrl": "",
  "searchActor": "class.detail@tag.p.1",
  "searchArea": "tag.li.2@text",
  "searchDesc": "",
  "searchDirector": "class.detail@tag.p.0",
  "searchImg": "class.thumb@tag.a.0@data-original",
  "searchList": "class.stui-pannel_bd@tag.li",
  "searchName": "tag.h3@text",
  "searchNoteUrl": "tag.a.0@href",
  "searchRemark": "class.thumb@tag.a.0@tag.span.2@text",
  "searchUrl": "https://www.91kanju.com/vod-search-wd-searchKey.html",
  "searchYear": "",
  "serialNumber": 41,
  "sortName": "",
  "sortNameList": "",
  "sortUrlList": "",
  "sourceGroup": "",
  "sourceName": "91看剧",
  "sourceUrl": "https://www.91kanju.com",
  "weight": 0
},
{
  "detailActor": "",
  "detailArea": "",
  "detailDesc": "",
  "detailDirector": "",
  "detailImg": "",
  "detailNoteUrl": "",
  "detailRemark": "",
  "detailUi": "1",
  "detailYear": "",
  "discern": "",
  "enable": true,
  "enableFind": false,
  "exclude": "",
  "findActor": "",
  "findArea": "",
  "findDesc": "",
  "findDirector": "",
  "findImg": "",
  "findList": "",
  "findName": "",
  "findNoteUrl": "",
  "findRemark": "",
  "findUrl": "",
  "findYear": "",
  "httpUserAgent": "",
  "loginText": "",
  "loginUrl": "",
  "parserType": "3",
  "parserUrl": "",
  "play": "",
  "playHeader": "",
  "playList": "",
  "playName": "",
  "playUrl": "list[0].vod_play_url",
  "reqUrl": "",
  "searchActor": "vod_actor",
  "searchArea": "vod_area",
  "searchDesc": "vod_content@js:java.Fhtml(result)",
  "searchDirector": "vod_director",
  "searchImg": "vod_pic",
  "searchList": "list[*]",
  "searchName": "vod_name",
  "searchNoteUrl": "http://zy.kuluni.cn/api.php/provide/vod/?ac=videolist&ids={$.vod_id}",
  "searchRemark": "vod_remarks",
  "searchUrl": "http://zy.kuluni.cn/api.php/provide/vod/?ac=videolist&wd=searchKey",
  "searchYear": "vod_year",
  "serialNumber": 1,
  "sortName": "",
  "sortNameList": "",
  "sortUrlList": "",
  "sourceGroup": "",
  "sourceName": "零度资源",
  "sourceUrl": "http://zy.kuluni.cn",
  "weight": 0
},

{
  "detailActor": "",
  "detailArea": "",
  "detailDesc": "",
  "detailDirector": "",
  "detailImg": "",
  "detailNoteUrl": "",
  "detailRemark": "",
  "detailUi": "1",
  "detailYear": "",
  "discern": "",
  "enable": true,
  "enableFind": false,
  "exclude": "",
  "findActor": "",
  "findArea": "",
  "findDesc": "",
  "findDirector": "",
  "findImg": "",
  "findList": "",
  "findName": "",
  "findNoteUrl": "",
  "findRemark": "",
  "findUrl": "",
  "findYear": "",
  "httpUserAgent": "",
  "loginText": "",
  "loginUrl": "",
  "parserType": "3",
  "parserUrl": "",
  "play": "",
  "playHeader": "",
  "playList": "",
  "playName": "",
  "playUrl": "list[0].vod_play_url",
  "reqUrl": "",
  "searchActor": "vod_actor",
  "searchArea": "vod_area",
  "searchDesc": "vod_content@js:java.Fhtml(result)",
  "searchDirector": "vod_director",
  "searchImg": "vod_pic",
  "searchList": "list[*]",
  "searchName": "vod_name",
  "searchNoteUrl": "http://zy.yilans.net:8090/api.php/provide/vod/?ac=videolist&ids={$.vod_id}",
  "searchRemark": "vod_remarks",
  "searchUrl": "http://zy.yilans.net:8090/api.php/provide/vod/?ac=videolist&wd=searchKey",
  "searchYear": "vod_year",
  "serialNumber": 15,
  "sortName": "",
  "sortNameList": "",
  "sortUrlList": "",
  "sourceGroup": "",
  "sourceName": "8090资源",
  "sourceUrl": "http://zy.yilans.net:8090",
  "weight": 0
},
{
  "detailActor": "",
  "detailArea": "",
  "detailDesc": "",
  "detailDirector": "",
  "detailImg": "",
  "detailNoteUrl": "",
  "detailRemark": "",
  "detailUi": "1",
  "detailYear": "",
  "discern": "",
  "enable": true,
  "enableFind": false,
  "exclude": "",
  "findActor": "",
  "findArea": "",
  "findDesc": "",
  "findDirector": "",
  "findImg": "",
  "findList": "",
  "findName": "",
  "findNoteUrl": "",
  "findRemark": "",
  "findUrl": "",
  "findYear": "",
  "httpUserAgent": "",
  "loginText": "",
  "loginUrl": "",
  "parserType": "3",
  "parserUrl": "",
  "play": "",
  "playHeader": "",
  "playList": "",
  "playName": "",
  "playUrl": "list[0].vod_play_url",
  "reqUrl": "",
  "searchActor": "vod_actor",
  "searchArea": "vod_area",
  "searchDesc": "vod_content@js:java.Fhtml(result)",
  "searchDirector": "vod_director",
  "searchImg": "vod_pic",
  "searchList": "list[*]",
  "searchName": "vod_name",
  "searchNoteUrl": "http://api.appearoo.top/api.php/provide/vod/?ac=videolist&ids={$.vod_id}",
  "searchRemark": "vod_remarks",
  "searchUrl": "http://api.appearoo.top/api.php/provide/vod/?ac=videolist&wd=searchKey",
  "searchYear": "vod_year",
  "serialNumber": 15,
  "sortName": "",
  "sortNameList": "",
  "sortUrlList": "",
  "sourceGroup": "",
  "sourceName": "萌果资源",
  "sourceUrl": "http://api.appearoo.top",
  "weight": 0
},
{
  "detailActor": "class.albumDetailMedia@tag.li.2@text",
  "detailArea": "",
  "detailDesc": "class.movie_story3@text",
  "detailDirector": "class.albumDetailMedia@tag.li.1@text",
  "detailImg": "",
  "detailNoteUrl": "",
  "detailRemark": "class.albumDetailMedia@tag.li.3@text",
  "detailUi": "1",
  "detailYear": "class.albumDetailMedia@tag.li.0@text",
  "discern": "",
  "enable": true,
  "enableFind": true,
  "exclude": "",
  "findActor": "",
  "findArea": "",
  "findDesc": "",
  "findDirector": "",
  "findImg": "",
  "findList": "",
  "findName": "",
  "findNoteUrl": "",
  "findRemark": "",
  "findUrl": "",
  "findYear": "",
  "httpUserAgent": "",
  "loginText": "",
  "loginUrl": "",
  "parserType": "4",
  "parserUrl": "",
  "play": "",
  "playHeader": "",
  "playList": "class.mod-main.0@tag.li",
  "playName": "tag.a@title",
  "playUrl": "tag.a@href@js:result.replace('/player/','https://m.rijutv.com/player/')",
  "reqUrl": "",
  "searchActor": "class.cont@tag.li.1@text@js:result.replace('主演:','')",
  "searchArea": "",
  "searchDesc": "class.cont@tag.li.2@text",
  "searchDirector": "",
  "searchImg": "tag.img.0@data-original",
  "searchList": "class.searchList@class.searchItem",
  "searchName": "tag.h3@text",
  "searchNoteUrl": "class.searchItem@tag.a@href",
  "searchRemark": "",
  "searchUrl": "https://m.rijutv.com/index.php?c=so&module=video&keyword=searchKey",
  "searchYear": "class.cont@tag.li.0@text",
  "serialNumber": 6,
  "sortName": "",
  "sortNameList": "",
  "sortUrlList": "",
  "sourceGroup": "",
  "sourceName": "日剧TV",
  "sourceUrl": "https://m.rijutv.com",
  "weight": 0
},
    
    {
        "detailActor": "",
        "detailArea": "",
        "detailDesc": "class.movie_story3@text",
        "detailDirector": "",
        "detailImg": "",
        "detailNoteUrl": "",
        "detailRemark": "",
        "detailUi": "2",
        "detailYear": "",
        "enable": true,
        "enableFind": true,
        "exclude": "",
        "findActor": "",
        "findArea": "",
        "findDesc": "",
        "findDirector": "",
        "findImg": "",
        "findList": "",
        "findName": "",
        "findNoteUrl": "",
        "findRemark": "",
        "findUrl": "",
        "findYear": "",
        "httpUserAgent": "",
        "loginText": "",
        "loginUrl": "",
        "parserType": "1",
        "parserUrl": "",
        "play": "",
        "playHeader": "",
        "playList": "-//ul[@class='down-list']/li",
        "playName": "//div/span/a/text()@js:result.replace(/magnet:(\\S*)dn=/,'')",
        "playUrl": "//div/span/a/@href",
        "reqUrl": "",
        "searchActor": "tag.li.1@text",
        "searchArea": "tag.li.4@text",
        "searchDesc": "",
        "searchDirector": "",
        "searchImg": "tag.a@tag.img@data-original",
        "searchList": "class.movList4",
        "searchName": "tag.a.1@text",
        "searchNoteUrl": "tag.a.0@href",
        "searchRemark": "tag.li.3@text",
        "searchUrl": "https://www.xlc2020.com/vod-search-id-searchKey-p-1.html",
        "searchYear": "tag.span@text",
        "serialNumber": 6,
        "sortName": "//a//text()",
        "sortNameList": "//ul[@class='tab-header tab-info']/li",
        "sortUrlList": "//div[@class='col-box col-infomation']/div/div/div/div",
        "sourceGroup": "",
        "sourceName": "迅雷仓",
        "sourceUrl": "https://www.xlc2020.com",
        "weight": 0
    },
    {
        "detailActor": "//meta[@name='description']@content##地区：(.*)年份：##$1###",
        "detailArea": "",
        "detailDesc": "class.ct-l@text",
        "detailDirector": "",
        "detailImg": "",
        "detailNoteUrl": "",
        "detailRemark": "",
        "detailUi": "2",
        "detailYear": "",
        "enable": true,
        "enableFind": false,
        "exclude": "",
        "findActor": "",
        "findArea": "",
        "findDesc": "",
        "findDirector": "",
        "findImg": "",
        "findList": "",
        "findName": "",
        "findNoteUrl": "",
        "findRemark": "",
        "findUrl": "",
        "findYear": "",
        "httpUserAgent": "",
        "loginText": "",
        "loginUrl": "",
        "parserType": "1",
        "parserUrl": "",
        "play": "",
        "playHeader": "",
        "playList": "tag.table@tag.td",
        "playName": "tag.a@text",
        "playUrl": "tag.a@href",
        "reqUrl": "",
        "searchActor": "",
        "searchArea": "",
        "searchDesc": "",
        "searchDirector": "",
        "searchImg": "tag.a@tag.img@data-original",
        "searchList": "class.index-area@tag.li",
        "searchName": "tag.a@title",
        "searchNoteUrl": "tag.a@href",
        "searchRemark": "tag.a@tag.p.4@text",
        "searchUrl": "https://www.dygang.org/e/search/index.php@keyboard=searchKey&show=title",
        "searchYear": "",
        "serialNumber": 7,
        "sortName": "",
        "sortNameList": "",
        "sortUrlList": "",
        "sourceGroup": "",
        "sourceName": "6V电影",
        "sourceUrl": "https://www.dygang.org",
        "weight": 0
    },

{
  "detailActor": "class.myui-content__detail.0@class.data.2@text",
  "detailArea": "class.myui-content__detail.0@class.data.0@text##地区：(.*)年份：##$1###",
  "detailDesc": "class.sketch@text",
  "detailDirector": "class.myui-content__detail.0@class.data.3@text",
  "detailImg": "",
  "detailNoteUrl": "",
  "detailRemark": "",
  "detailUi": "1",
  "detailYear": "class.myui-content__detail.0@class.data.0@text##年份：(.*)##$1###",
  "discern": "",
  "enable": true,
  "enableFind": false,
  "exclude": "",
  "findActor": "",
  "findArea": "",
  "findDesc": "",
  "findDirector": "",
  "findImg": "",
  "findList": "",
  "findName": "",
  "findNoteUrl": "",
  "findRemark": "",
  "findUrl": "",
  "findYear": "",
  "httpUserAgent": "",
  "loginText": "",
  "loginUrl": "",
  "parserType": "4",
  "parserUrl": "",
  "play": "",
  "playHeader": "",
  "playList": "id.playlist1@tag.li",
  "playName": "tag.a.0@text",
  "playUrl": "tag.a.0@href@js:'https://tv.ci' + result",
  "reqUrl": "",
  "searchActor": "class.detail@tag.p.1@text##主演：##",
  "searchArea": "class.detail@tag.p.2@text##地区：(.*)年份：##$1###",
  "searchDesc": "",
  "searchDirector": "class.detail@tag.p.0@text##导演：##",
  "searchImg": "class.thumb.0@tag.a.0@data-original",
  "searchList": "class.myui-panel_bd@tag.li",
  "searchName": "class.thumb@tag.a.0@title",
  "searchNoteUrl": "class.detail.0@class.title.0@tag.a.0@href",
  "searchRemark": "tag.a.0@class.pic-text@text",
  "searchUrl": "https://tv.ci/s/--.html?wd=searchKey",
  "searchYear": "class.detail@tag.p.2@text##年份：(.*)##$1###",
  "serialNumber": 11,
  "sortName": "",
  "sortNameList": "",
  "sortUrlList": "",
  "sourceGroup": "",
  "sourceName": "大师兄影视",
  "sourceUrl": "https://tv.ci",
  "weight": 0
},
    
    {
        "detailActor": "",
        "detailArea": "",
        "detailDesc": "content",
        "detailDirector": "",
        "detailImg": "homePicUrl",
        "detailNoteUrl": "",
        "detailRemark": "",
        "detailUi": "2",
        "detailYear": "",
        "enable": true,
        "enableFind": false,
        "exclude": "",
        "findActor": "",
        "findArea": "",
        "findDesc": "",
        "findDirector": "",
        "findImg": "",
        "findList": "",
        "findName": "",
        "findNoteUrl": "",
        "findRemark": "",
        "findUrl": "",
        "findYear": "",
        "httpUserAgent": "",
        "loginText": "",
        "loginUrl": "",
        "parserType": "1",
        "parserUrl": "",
        "play": "",
        "playHeader": "",
        "playList": "",
        "playName": "",
        "playUrl": "@T$.downloadUrl",
        "reqUrl": "",
        "searchActor": "",
        "searchArea": "name##\\[(.*)\\]##$1###",
        "searchDesc": "",
        "searchDirector": "",
        "searchImg": "",
        "searchList": "rows[*]",
        "searchName": "name##《(.*)》##$1###",
        "searchNoteUrl": "http://m.dydytt.net:8080/adminapi/api/movieDetail.json?categoryId=9&movieDetailId={$.id}",
        "searchRemark": "name##》(.*)##$1###",
        "searchUrl": "http://m.dydytt.net:8080/adminapi/api/movieList.json?categoryId=0&page=1&searchContent=searchKey",
        "searchYear": "name##(\\d{4})##$1###",
        "serialNumber": 9,
        "sortName": "",
        "sortNameList": "",
        "sortUrlList": "",
        "sourceGroup": "",
        "sourceName": "电影天堂",
        "sourceUrl": "http://m.dydytt.net",
        "weight": 0
    },


    {
  "detailActor": "class.vod-n-l.0@tag.p.1@text##主演：##",
  "detailArea": "class.vod-n-l.0@tag.p.4@text##地区：##",
  "detailDesc": "",
  "detailDirector": "class.vod-n-l.0@tag.p.3@text##导演：##",
  "detailImg": "class.vod-n-img.0@tag.img.0@src",
  "detailNoteUrl": "",
  "detailRemark": "",
  "detailUi": "1",
  "detailYear": "class.vod-n-l.0@tag.p.5@text##更新：##",
  "discern": "",
  "enable": true,
  "enableFind": false,
  "exclude": "/dqxzjs.m3u8,/index.m3u8?,/youku21json.m3u8?,/index.ng?,/cityjson.ip?,/indexh5.m3u8?,/urldata.m3u8?,/letvsv.m3u8?,pptv/sj.1.m3u8?,/bilibili.m3u8?",
  "findActor": "",
  "findArea": "",
  "findDesc": "",
  "findDirector": "",
  "findImg": "",
  "findList": "",
  "findName": "",
  "findNoteUrl": "",
  "findRemark": "",
  "findUrl": "",
  "findYear": "",
  "httpUserAgent": "Mozilla/5.0 (Linux; Android 10) AppleWebKit/537.36 (KHTML, like Gecko) Chrome/78.0.3904.108 Mobile Safari/537.36",
  "loginText": "",
  "loginUrl": "",
  "parserType": "4",
  "parserUrl": "",
  "play": "",
  "playHeader": "",
  "playList": "-tag.li",
  "playName": "tag.a.0@text",
  "playUrl": "tag.a.0@href@js:'http://m.f4yy.com' + result",
  "reqUrl": "",
  "searchActor": "",
  "searchArea": "",
  "searchDesc": "",
  "searchDirector": "",
  "searchImg": "class.loading@data-original",
  "searchList": "class.new_tab_img.0@tag.li",
  "searchName": "class.list_info.0@tag.h2.0@tag.a.0@text",
  "searchNoteUrl": "tag.a.0@href",
  "searchRemark": "class.list_info@tag.p.3@text##状态：##",
  "searchUrl": "http://m.f4yy.com/vod-search-pg-1-wd-searchKey.html",
  "searchYear": "",
  "serialNumber": 42,
  "sortName": "tag.span.1@text",
  "sortNameList": "class.play-title",
  "sortUrlList": "class.plau-ul-list",
  "sourceGroup": "",
  "sourceName": "喝茶",
  "sourceUrl": "http://m.f4yy.com",
  "weight": 0
},
    
   
    {
        "detailActor": "",
        "detailArea": "",
        "detailDesc": "",
        "detailDirector": "",
        "detailImg": "",
        "detailNoteUrl": "",
        "detailRemark": "",
        "detailUi": "1",
        "detailYear": "",
        "enable": true,
        "enableFind": false,
        "exclude": "",
        "findActor": "",
        "findArea": "",
        "findDesc": "",
        "findDirector": "",
        "findImg": "",
        "findList": "",
        "findName": "",
        "findNoteUrl": "",
        "findRemark": "",
        "findUrl": "",
        "findYear": "",
        "httpUserAgent": "",
        "loginText": "",
        "loginUrl": "",
        "parserType": "3",
        "parserUrl": "",
        "play": "",
        "playHeader": "",
        "playList": "",
        "playName": "",
        "playUrl": "list[0].vod_play_url",
        "reqUrl": "",
        "searchActor": "vod_actor",
        "searchArea": "vod_area",
        "searchDesc": "vod_content@js:java.Fhtml(result)",
        "searchDirector": "vod_director",
        "searchImg": "vod_pic",
        "searchList": "list[*]",
        "searchName": "vod_name",
        "searchNoteUrl": "https://m3u8.tiankongapi.com/api.php/provide/vod/?ac=videolist&ids={$.vod_id}",
        "searchRemark": "vod_remarks",
        "searchUrl": "https://m3u8.tiankongapi.com/api.php/provide/vod/?ac=videolist&wd=searchKey",
        "searchYear": "vod_year",
        "serialNumber": 15,
        "sortName": "",
        "sortNameList": "",
        "sortUrlList": "",
        "sourceGroup": "",
        "sourceName": "天空资源",
        "sourceUrl": "https://m3u8.tiankongapi.com",
        "weight": 0
    },
    {
        "detailActor": ".actors[*].name@js:java.Fhtml(result)",
        "detailArea": ".area.title",
        "detailDesc": ".description",
        "detailDirector": ".directors[*].name@js:java.Fhtml(result)",
        "detailImg": "",
        "detailNoteUrl": "",
        "detailRemark": "",
        "detailUi": "1",
        "detailYear": ".year.title",
        "enable": true,
        "enableFind": true,
        "exclude": "",
        "findActor": "",
        "findArea": "",
        "findDesc": "description",
        "findDirector": "",
        "findImg": "images.poster",
        "findList": "data[*]",
        "findName": "title",
        "findNoteUrl": "http://api2.rinhome.com/api/node/detail?token=&id={$.id}",
        "findRemark": "torrents.zh[0].title",
        "findUrl": "电影::http://api2.rinhome.com/api/bt/list?genere_id&order&lang&keywords&sort=update&category_id=5&page=searchPage&limit=24\n电视剧::http://api2.rinhome.com/api/bt/list?genere_id&order&lang&keywords&sort=update&category_id=14&page=searchPage&limit=24\n动漫::http://api2.rinhome.com/api/bt/list?genere_id&order&lang&keywords&sort=update&category_id=19&page=searchPage&limit=24",
        "findYear": "year&&duration",
        "httpUserAgent": "{\"JPAUTH\": \"7wtdqf/qrZv1SjOYwbTfIiBd8fPjGIvGO3R0KQjkYOaQ\",\r\n\"user-agent\": \"jianpian-android/327\"}",
        "loginText": "",
        "loginUrl": "",
        "parserType": "1",
        "parserUrl": "",
        "play": "",
        "playHeader": "",
        "playList": ".btbo_downlist[*]",
        "playName": "title",
        "playUrl": "url",
        "reqUrl": "",
        "searchActor": "",
        "searchArea": "",
        "searchDesc": "",
        "searchDirector": "",
        "searchImg": "thumbnail",
        "searchList": "data[*]",
        "searchName": "title",
        "searchNoteUrl": "http://api2.rinhome.com/api/node/detail?token=&id={$.id}",
        "searchRemark": "mask",
        "searchUrl": "http://api2.rinhome.com/api/video/search?key=searchKey&page=1",
        "searchYear": "",
        "serialNumber": 16,
        "sortName": "",
        "sortNameList": "",
        "sortUrlList": "",
        "sourceGroup": "",
        "sourceName": "荐片",
        "sourceUrl": "http://api2.rinhome.com",
        "weight": 0
    },
    {
  "detailActor": "class.stui-content-detail@tag.data.1@text",
  "detailArea": "class.stui-content-detail@class.text-muted.1",
  "detailDesc": "",
  "detailDirector": "",
  "detailImg": "tag.img@data-original",
  "detailNoteUrl": "@tag.a@href@js:result.replace('/vodplay/','https://www.zhenbuka2.com/vodplay/')",
  "detailRemark": "",
  "detailUi": "1",
  "detailYear": "class.stui-content-detail@class.text-muted.2",
  "discern": "",
  "enable": true,
  "enableFind": true,
  "exclude": "",
  "findActor": "",
  "findArea": "",
  "findDesc": "",
  "findDirector": "",
  "findImg": "tag.a@data-original",
  "findList": "class.stui-pannel_bd@tag.li",
  "findName": "tag.h4@text",
  "findNoteUrl": "tag.a@href",
  "findRemark": "tag.span.1@text",
  "findUrl": "电影::https://www.zhenbuka3.com/vodtype/1-searchPage/\n电视剧::https://www.zhenbuka3.com/vodtype/2-searchPage/\n综艺::https://www.zhenbuka3.com/vodtype/3-searchPage/\n动漫::https://www.zhenbuka3.com/vodtype/4-searchPage/",
  "findYear": "",
  "httpUserAgent": "Mozilla/5.0 (Linux; U; Android 8.0.0; zh-cn; Mi Note 2 Build/OPR1.170623.032) AppleWebKit/537.36 (KHTML, like Gecko) Version/4.0 Chrome/61.0.3163.128 Mobile Safari/537.36 XiaoMi/MiuiBrowser/10.1.1",
  "loginText": "",
  "loginUrl": "",
  "parserType": "4",
  "parserUrl": "",
  "play": "",
  "playHeader": "",
  "playList": "class.stui-pannel_bd@tag.li",
  "playName": "class.stui-content-detail@tag.title",
  "playUrl": "tag.a@href<js>'https://www.zhenbuka3.com' + result</js>",
  "reqUrl": "",
  "searchActor": "",
  "searchArea": "",
  "searchDesc": "",
  "searchDirector": "",
  "searchImg": "",
  "searchList": "class.stui-vodlist_media@li",
  "searchName": "class.detail@tag.a",
  "searchNoteUrl": "",
  "searchRemark": "",
  "searchUrl": "https://www.zhenbuka2.com/vodsearch/-------------/?wd=searchKey",
  "searchYear": "",
  "serialNumber": 1,
  "sortName": "",
  "sortNameList": "",
  "sortUrlList": "",
  "sourceGroup": "",
  "sourceName": "真不卡",
  "sourceUrl": "www.zhenbuka2.com",
  "weight": 0
},
    {
        "detailActor": "class.info@tag.li.4@text##主演：##@js:result.replace('主持：','')",
        "detailArea": "class.info@tag.li.7@text##国家/地区：##",
        "detailDesc": "class.details-content-all@text",
        "detailDirector": "class.info@tag.li.6@text##导演：##",
        "detailImg": "",
        "detailNoteUrl": "",
        "detailRemark": "class.info@tag.li.1@text##状态： ##@js:result.replace('清晰：','')",
        "detailUi": "1",
        "detailYear": "class.info@tag.li.10@text##([^-]+)##$1###@js:result.replace('首播时间：','').replace('年代：','').replace('上映时间：','')",
        "enable": true,
        "enableFind": true,
        "exclude": "",
        "findActor": "",
        "findArea": "",
        "findDesc": "",
        "findDirector": "",
        "findImg": "tag.a.0@data-original",
        "findList": "class.box-video-list@tag.li",
        "findName": "tag.a@title",
        "findNoteUrl": "tag.a.0@href",
        "findRemark": "class.note@text",
        "findUrl": "电影::http://www.doubiekan.net/?s=vod-type-id-1-p-searchPage.html\n电视剧::http://www.doubiekan.net/?s=vod-type-id-2-p-searchPage.html\n动漫::http://www.doubiekan.net/?s=vod-type-id-3-p-searchPage.html\n综艺::http://www.doubiekan.net/?s=vod-type-id-4-p-searchPage.html\n微电影::http://www.doubiekan.net/?s=vod-type-id-35-p-searchPage.html",
        "findYear": "class.score@text",
        "httpUserAgent": "Mozilla/5.0 (Linux; Android 7.0; wv) AppleWebKit/537.36 (KHTML, like Gecko) Version/4.0 Chrome/56.0.2924.87 Mobile Safari/537.36",
        "loginText": "",
        "loginUrl": "",
        "parserType": "4",
        "parserUrl": "",
        "play": "",
        "playHeader": "",
        "playList": "-tag.li",
        "playName": "tag.a@text",
        "playUrl": "tag.a@href<js>'http://www.doubiekan.net' + result</js>",
        "reqUrl": "",
        "searchActor": "class.details-info@tag.li.4@text##主演：##@js:result.replace('主持：','')",
        "searchArea": "class.details-info@tag.li.7@text##国家/地区：##",
        "searchDesc": "class.details-content-default@text##详细介绍：##",
        "searchDirector": "class.details-info@tag.li.6@text##导演：##",
        "searchImg": "tag.a.0@data-original",
        "searchList": "class.container@class.box-main-content@class.details-info-min",
        "searchName": "tag.a@title",
        "searchNoteUrl": "tag.a.0@href",
        "searchRemark": "class.details-info@tag.li.2@text##状态：##",
        "searchUrl": "http://www.doubiekan.net/search/searchKey-searchPage.html",
        "searchYear": "class.details-info@tag.li.10@text##([^-]+)##$1###@js:result.replace('首播时间：','').replace('年代：','').replace('上映时间：','')",
        "serialNumber": 17,
        "sortName": "tag.a@text",
        "sortNameList": "class.details-play-title@tag.ul@tag.li",
        "sortUrlList": "class.playlist@tag.ul",
        "sourceGroup": "",
        "sourceName": "逗别看",
        "sourceUrl": "http://www.doubiekan.net",
        "weight": 0
    },
    {
        "detailActor": "class.stui-content__detail@tag.p.0@text##主演：##@js:result.replace('主持：','')",
        "detailArea": "class.stui-content__detail@tag.p.2@text##地区：(.*)年份：##$1###",
        "detailDesc": "class.stui-content__detail@class.detail-content@text",
        "detailDirector": "class.stui-content__detail@tag.p.1@text##导演：##",
        "detailImg": "",
        "detailNoteUrl": "",
        "detailRemark": "class.stui-content__thumb@class.pic-text@text",
        "detailUi": "1",
        "detailYear": "class.stui-content__detail@tag.p.2@text##年份：(.*)##$1###",
        "enable": true,
        "enableFind": true,
        "exclude": "",
        "findActor": "",
        "findArea": "",
        "findDesc": "",
        "findDirector": "",
        "findImg": "tag.a.0@data-original",
        "findList": "class.stui-vodlist@tag.li",
        "findName": "tag.a.0@title",
        "findNoteUrl": "tag.a.0@href",
        "findRemark": "tag.a.0@tag.span.1@text",
        "findUrl": "电影::http://www.8haodyy.com/frim/1-searchPage.html\n电视剧::http://www.8haodyy.com/frim/2-searchPage.html\n综艺::http://www.8haodyy.com/frim/3-searchPage.html\n动漫::http://www.8haodyy.com/frim/4-searchPage.html",
        "findYear": "",
        "httpUserAgent": "Dalvik/2.1.0 (Linux; U; Android 7.0; HUAWEI MLA-AL10 Build/HUAWEIMLA-AL10)",
        "loginText": "",
        "loginUrl": "",
        "parserType": "4",
        "parserUrl": "",
        "play": "",
        "playHeader": "",
        "playList": "tag.li",
        "playName": "tag.a@title",
        "playUrl": "tag.a@href<js>'@Header:{User-Agent:Lavf/57.83.100}http://www.8haodyy.com/' + result</js>",
        "reqUrl": "api.jxyiyi.com/index/",
        "searchActor": "class.detail@tag.p.1@text##主演：##@js:result.replace('主持：','')",
        "searchArea": "class.detail@tag.p.2@text##地区：(.*)年份：##$1###",
        "searchDesc": "",
        "searchDirector": "class.detail@tag.p.0@text##导演：##",
        "searchImg": "tag.a.0@data-original",
        "searchList": "class.col-lg-wide-75@class.stui-vodlist__media@tag.li",
        "searchName": "tag.a.0@title",
        "searchNoteUrl": "tag.a.0@href",
        "searchRemark": "tag.a.0@tag.span.1@text",
        "searchUrl": "http://www.8haodyy.com/search.php?searchword=searchKey",
        "searchYear": "class.detail@tag.p.2@text##年份：(.*)##$1###",
        "serialNumber": 18,
        "sortName": "tag.h3@text",
        "sortNameList": "id.playlist@class.bottom-line",
        "sortUrlList": "class.stui-content__playlist",
        "sourceGroup": "发现",
        "sourceName": "八号影院",
        "sourceUrl": "http://www.8haodyy.com",
        "weight": 0
    },

    
    {
  "detailActor": "class.line1@text##主演：(.*)导演：##$1###",
  "detailArea": "class.data@text##地区：(.*)年份：##$1###",
  "detailDesc": "class.stui-content__detail@tag.span.9@text",
  "detailDirector": "class.data@text##导演：(.*)##",
  "detailImg": "",
  "detailNoteUrl": "",
  "detailRegex": "",
  "detailRemark": "class.info@tag.li.1@text##状态： ##@js:result.replace('清晰：','')",
  "detailUi": "1",
  "detailYear": "class.data@text##年份：(.*)##$1###",
  "discern": "",
  "enable": true,
  "enableFind": true,
  "exclude": "",
  "findActor": "",
  "findArea": "",
  "findDesc": "",
  "findDirector": "tag.p@text",
  "findImg": "tag.a.0@data-original",
  "findList": "class.stui-vodlist@tag.li",
  "findName": "tag.a@title",
  "findNoteUrl": "tag.a.0@href",
  "findRemark": "class.pic-text@text",
  "findScreen": "",
  "findUrl": "电影::http://taoju.tv/list/1_searchPage.html\n电视剧::http://taoju.tv/list/2_searchPage.html\n动漫::http://taoju.tv/list/3_searchPage.html\n综艺::http://taoju.tv/list/4_searchPage.html\n",
  "findYear": "class.score@text",
  "httpUserAgent": "Mozilla/5.0 (Linux; U; Android 8.0.0; zh-cn; Mi Note 2 Build/OPR1.170623.032) AppleWebKit/537.36 (KHTML, like Gecko) Version/4.0 Chrome/61.0.3163.128 Mobile Safari/537.36 XiaoMi/MiuiBrowser/10.1.1",
  "loginText": "",
  "loginUrl": "",
  "parserType": "4",
  "parserUrl": "",
  "play": "",
  "playHeader": "",
  "playList": "-tag.li",
  "playName": "tag.a@text",
  "playUrl": "tag.a@href<js>'http://taoju.tv' + result</js>",
  "reqUrl": "",
  "searchActor": "class.details-info@tag.li.4@text##主演：##@js:result.replace('主持：','')",
  "searchArea": "class.details-info@tag.li.7@text##国家/地区：##",
  "searchDesc": "class.details-content-default@text##详细介绍：##",
  "searchDirector": "class.details-info@tag.li.6@text##导演：##",
  "searchImg": "tag.a.0@data-original",
  "searchList": "class.container@class.box-main-content@class.details-info-min",
  "searchName": "tag.a@title",
  "searchNoteUrl": "tag.a.0@href",
  "searchRemark": "class.details-info@tag.li.2@text##状态：##",
  "searchUrl": "http://taoju.tv/search.php@searchword=serarchKey&verfify=vpnn",
  "searchYear": "class.details-info@tag.li.10@text##([^-]+)##$1###@js:result.replace('首播时间：','').replace('年代：','').replace('上映时间：','')",
  "serialNumber": 100,
  "sortName": "tag.a@text",
  "sortNameList": "class.nav-tabs@tag.li",
  "sortUrlList": "class.stui-content__playlist@tag.ul",
  "sourceGroup": "",
  "sourceName": "奇优影视",
  "sourceUrl": "http://taoju.tv",
  "weight": 0
    },
    
    {
        "detailActor": "",
        "detailArea": "",
        "detailDesc": "class.detail-sketch@text",
        "detailDirector": "",
        "detailImg": "",
        "detailNoteUrl": "",
        "detailRemark": "",
        "detailUi": "1",
        "detailYear": "",
        "enable": true,
        "enableFind": false,
        "exclude": "",
        "findActor": "",
        "findArea": "",
        "findDesc": "",
        "findDirector": "",
        "findImg": "",
        "findList": "",
        "findName": "",
        "findNoteUrl": "",
        "findRemark": "",
        "findUrl": "",
        "findYear": "",
        "httpUserAgent": "Mozilla/5.0 (Linux; Android 7.0; wv) AppleWebKit/537.36 (KHTML, like Gecko) Version/4.0 Chrome/56.0.2924.87 Mobile Safari/537.36",
        "loginText": "",
        "loginUrl": "",
        "parserType": "4",
        "parserUrl": "",
        "play": "",
        "playHeader": "",
        "playList": "-tag.li",
        "playName": "tag.a@text",
        "playUrl": "tag.a@href<js>'http://www.nangua5.com' + result</js>",
        "reqUrl": "",
        "searchActor": "class.details-info@tag.li.4@text##主演：##@js:result.replace('主持：','')",
        "searchArea": "class.details-info@tag.li.7@text##国家/地区：##",
        "searchDesc": "class.details-content-default@text##详细介绍：##",
        "searchDirector": "class.details-info@tag.li.6@text##导演：##",
        "searchImg": "tag.a.0@data-original",
        "searchList": "class.container@class.box-main-content@class.details-info-min",
        "searchName": "tag.a@title",
        "searchNoteUrl": "tag.a.0@href",
        "searchRemark": "class.details-info@tag.li.2@text##状态：##",
        "searchUrl": "http://www.nangua5.com/search/searchKey-searchPage.html",
        "searchYear": "class.details-info@tag.li.10@text##([^-]+)##$1###@js:result.replace('首播时间：','').replace('年代：','').replace('上映时间：','')",
        "serialNumber": 23,
        "sortName": "tag.a@text",
        "sortNameList": "class.details-play-title@tag.ul@tag.li",
        "sortUrlList": "class.playlist@tag.ul",
        "sourceGroup": "",
        "sourceName": "南瓜五",
        "sourceUrl": "http://www.nangua5.com",
        "weight": 0
    },
    
    {
        "detailActor": "",
        "detailArea": "",
        "detailDesc": "class.detail-intro-txt@text",
        "detailDirector": "",
        "detailImg": "",
        "detailNoteUrl": "",
        "detailRemark": "",
        "detailUi": "1",
        "detailYear": "",
        "enable": true,
        "enableFind": false,
        "exclude": "",
        "findActor": "",
        "findArea": "",
        "findDesc": "",
        "findDirector": "",
        "findImg": "",
        "findList": "",
        "findName": "",
        "findNoteUrl": "",
        "findRemark": "",
        "findUrl": "",
        "findYear": "",
        "httpUserAgent": "Mozilla/5.0 (Linux; Android 7.0; wv) AppleWebKit/537.36 (KHTML, like Gecko) Version/4.0 Chrome/56.0.2924.87 Mobile Safari/537.36",
        "loginText": "",
        "loginUrl": "",
        "parserType": "4",
        "parserUrl": "",
        "play": "",
        "playHeader": "",
        "playList": "-tag.li",
        "playName": "tag.a@text",
        "playUrl": "tag.a@href<js>'http://www.wuaitao.org' + result</js>",
        "reqUrl": "",
        "searchActor": "tag.li.2@text##主演：##",
        "searchArea": "",
        "searchDesc": "",
        "searchDirector": "tag.li.1@text##导演：##",
        "searchImg": "tag.a.0@img@src",
        "searchList": "class.detail-search@class.detail-wrap",
        "searchName": "tag.a.0@title",
        "searchNoteUrl": "tag.a.0@href",
        "searchRemark": "tag.li.3@text##评分：##",
        "searchUrl": "http://www.wuaitao.org/vod-search-pg-searchPage-wd-searchKey.html",
        "searchYear": "tag.li.0@text##年代：##",
        "serialNumber": 25,
        "sortName": "text",
        "sortNameList": "class.filmSources@tag.ul@tag.li",
        "sortUrlList": "class.wrap",
        "sourceGroup": "",
        "sourceName": "吾爱淘",
        "sourceUrl": "http://www.wuaitao.org",
        "weight": 0
    },
    
    {
        "detailActor": "",
        "detailArea": "",
        "detailDesc": "",
        "detailDirector": "",
        "detailImg": "",
        "detailNoteUrl": "",
        "detailRemark": "",
        "detailUi": "1",
        "detailYear": "",
        "enable": true,
        "enableFind": false,
        "exclude": "",
        "findActor": "",
        "findArea": "",
        "findDesc": "",
        "findDirector": "",
        "findImg": "",
        "findList": "",
        "findName": "",
        "findNoteUrl": "",
        "findRemark": "",
        "findUrl": "",
        "findYear": "",
        "httpUserAgent": "okhttp/3.12.0",
        "loginText": "",
        "loginUrl": "",
        "parserType": "1",
        "parserUrl": "",
        "play": "",
        "playHeader": "",
        "playList": ".episodes[*]",
        "playName": "episode",
        "playUrl": "@Header:{User-Agent:Lavf/57.83.100}{$.playurl}",
        "reqUrl": "",
        "searchActor": "starName",
        "searchArea": "vod_class",
        "searchDesc": "brief",
        "searchDirector": "",
        "searchImg": "videoCover",
        "searchList": "data[*]",
        "searchName": "videoName",
        "searchNoteUrl": "http://api.kunyu77.com/api.php/provide/videoPlaylist?ids={$.id}&pcode=030110000&version=1.7.2&devid=d719a0a0e1b73290aad51e9f24e7672f&package=com.xiaoxiaoVideo.app.android&sys=android&sysver=7.0&brand=HUAWEI&model=HUAWEI_MLA-AL10&sj=1593141375",
        "searchRemark": "msg",
        "searchUrl": "@Header:{\"version\":\"1.7.2\",\"token\":\"\"}http://api.kunyu77.com/api.php/provide/searchVideo?searchName=searchKey&pg=searchPage",
        "searchYear": "year",
        "serialNumber": 27,
        "sortName": "",
        "sortNameList": "",
        "sortUrlList": "",
        "sourceGroup": "",
        "sourceName": "七七影视",
        "sourceUrl": "http://api.kunyu77.com",
        "weight": 0
    },
    
    {
        "detailActor": "",
        "detailArea": "",
        "detailDesc": "",
        "detailDirector": "",
        "detailImg": "",
        "detailNoteUrl": "",
        "detailRemark": "",
        "detailUi": "1",
        "detailYear": "",
        "enable": true,
        "enableFind": false,
        "exclude": "",
        "findActor": "",
        "findArea": "",
        "findDesc": "",
        "findDirector": "",
        "findImg": "",
        "findList": "",
        "findName": "",
        "findNoteUrl": "",
        "findRemark": "",
        "findUrl": "",
        "findYear": "",
        "httpUserAgent": "okhttp/3.14.1",
        "loginText": "",
        "loginUrl": "",
        "parserType": "1",
        "parserUrl": "",
        "play": "",
        "playHeader": "",
        "playList": "",
        "playName": "",
        "playUrl": "",
        "reqUrl": "",
        "searchActor": "",
        "searchArea": "",
        "searchDesc": "",
        "searchDirector": "",
        "searchImg": "",
        "searchList": "",
        "searchName": "",
        "searchNoteUrl": "",
        "searchRemark": "",
        "searchUrl": "",
        "searchYear": "",
        "serialNumber": 29,
        "sortName": "",
        "sortNameList": "",
        "sortUrlList": "",
        "sourceGroup": "",
        "sourceName": "鱼渔影视",
        "sourceUrl": "http://42.194.187.127",
        "weight": 0
    },
    
    {
  "detailActor": "class.albumDetailMedia@tag.li.2@text",
  "detailArea": "",
  "detailDesc": "class.movie_story3@text",
  "detailDirector": "class.albumDetailMedia@tag.li.1@text",
  "detailImg": "",
  "detailNoteUrl": "",
  "detailRemark": "class.albumDetailMedia@tag.li.3@text",
  "detailUi": "1",
  "detailYear": "class.albumDetailMedia@tag.li.0@text",
  "discern": "",
  "enable": true,
  "enableFind": true,
  "exclude": "",
  "findActor": "",
  "findArea": "",
  "findDesc": "",
  "findDirector": "",
  "findImg": "",
  "findList": "",
  "findName": "",
  "findNoteUrl": "",
  "findRemark": "",
  "findUrl": "",
  "findYear": "",
  "httpUserAgent": "",
  "loginText": "",
  "loginUrl": "",
  "parserType": "4",
  "parserUrl": "",
  "play": "",
  "playHeader": "",
  "playList": "class.mod-main@tag.li",
  "playName": "tag.a@title",
  "playUrl": "tag.a@href@js:result.replace('/player/','https://m.hanjutv2020.com/player/')",
  "reqUrl": "",
  "searchActor": "class.cont@tag.li.1@text@js:result.replace('主演:','')",
  "searchArea": "",
  "searchDesc": "class.cont@tag.li.2@text",
  "searchDirector": "",
  "searchImg": "tag.img.0@data-original",
  "searchList": "class.searchList@class.searchItem",
  "searchName": "tag.h3@text",
  "searchNoteUrl": "class.searchItem@tag.a@href",
  "searchRemark": "",
  "searchUrl": "https://m.hanjutv2020.com/index.php?c=so&module=video&keyword=searchKey",
  "searchYear": "class.cont@tag.li.0@text",
  "serialNumber": 6,
  "sortName": "",
  "sortNameList": "",
  "sortUrlList": "",
  "sourceGroup": "",
  "sourceName": "韩剧TV",
  "sourceUrl": "https://m.hanjutv2020.com",
  "weight": 0
},

{
  "detailActor": "",
  "detailArea": "",
  "detailDesc": "class.movie_story3@text",
  "detailDirector": "",
  "detailImg": "",
  "detailNoteUrl": "",
  "detailRemark": "",
  "detailUi": "1",
  "detailYear": "",
  "discern": "",
  "enable": true,
  "enableFind": true,
  "exclude": "",
  "findActor": "",
  "findArea": "",
  "findDesc": "",
  "findDirector": "",
  "findImg": "tag.a@data-original",
  "findList": "class.item@tag.li",
  "findName": "class.title@tag.h5@text",
  "findNoteUrl": "tag.a@href",
  "findRemark": "",
  "findUrl": "科幻动作::https://www.meiju11.com/search.php?page=searchPage&searchtype=5&tid=13\\n悬疑烧脑::https://www.meiju11.com/search.php?page=searchPage&searchtype=5&tid=14\\n青春喜剧::https://www.meiju11.com/search.php?page=searchPage&searchtype=5&tid=15\\n精英文艺::https://www.meiju11.com/search.php?page=searchPage&searchtype=5&tid=16\\n卡通动漫::https://www.meiju11.com/search.php?page=searchPage&searchtype=5&tid=3\\n综艺选秀::https://www.meiju11.com/search.php?page=searchPage&searchtype=5&tid=4",
  "findYear": "",
  "httpUserAgent": "",
  "loginText": "",
  "loginUrl": "",
  "parserType": "4",
  "parserUrl": "",
  "play": "",
  "playHeader": "",
  "playList": "id.playlist1@tag.li",
  "playName": "tag.a@title",
  "playUrl": "tag.a@href@js:result.replace('/Play/','https://www.meiju11.com/Play/')",
  "reqUrl": "",
  "searchActor": "tag.li.0@text",
  "searchArea": "tag.li.2@text",
  "searchDesc": "",
  "searchDirector": "tag.li.1@text",
  "searchImg": "tag.a@style##background: url(.*)no##$1###@js:result.replace('(','').replace(')','')",
  "searchList": "class.hy-layout@class.hy-video-details@class.content@tag.dl",
  "searchName": "tag.h3@text",
  "searchNoteUrl": "tag.a.0@href",
  "searchRemark": "tag.span.1@text",
  "searchUrl": "https://www.meiju11.com/search.php?searchword=searchKey",
  "searchYear": "tag.li.5@text",
  "serialNumber": 37,
  "sortName": "",
  "sortNameList": "",
  "sortUrlList": "",
  "sourceGroup": "",
  "sourceName": "爱美剧",
  "sourceUrl": "https://www.meiju11.com",
  "weight": 0
},
{
  "detailActor": "class.albumDetailMedia@tag.li.2@text",
  "detailArea": "",
  "detailDesc": "class.movie_story3@text",
  "detailDirector": "class.albumDetailMedia@tag.li.1@text",
  "detailImg": "",
  "detailNoteUrl": "",
  "detailRemark": "class.albumDetailMedia@tag.li.3@text",
  "detailUi": "1",
  "detailYear": "class.albumDetailMedia@tag.li.0@text",
  "discern": "",
  "enable": true,
  "enableFind": true,
  "exclude": "",
  "findActor": "",
  "findArea": "",
  "findDesc": "",
  "findDirector": "",
  "findImg": "",
  "findList": "",
  "findName": "",
  "findNoteUrl": "",
  "findRemark": "",
  "findUrl": "",
  "findYear": "",
  "httpUserAgent": "",
  "loginText": "",
  "loginUrl": "",
  "parserType": "4",
  "parserUrl": "",
  "play": "",
  "playHeader": "",
  "playList": "class.stui-vodlist__head.0@tag.li@tag.a",
  "playName": "tag.a@text",
  "playUrl": "tag.a@href@js:result.replace('/play/','https://www.libvio.com/play/')",
  "reqUrl": "",
  "searchActor": "",
  "searchArea": "",
  "searchDesc": "",
  "searchDirector": "",
  "searchImg": "class.stui-vodlist__thumb@tag.a@data-original",
  "searchList": "class.stui-pannel__bd@tag.li",
  "searchName": "tag.h4@text",
  "searchNoteUrl": "class.stui-vodlist__thumb@tag.a@href",
  "searchRemark": "",
  "searchUrl": "https://www.libvio.com/search/-------------.html?wd=searchKey",
  "searchYear": "class.cont@tag.li.0@text",
  "serialNumber": 6,
  "sortName": "",
  "sortNameList": "",
  "sortUrlList": "",
  "sourceGroup": "",
  "sourceName": "libvio",
  "sourceUrl": "https://www.libvio.com",
  "weight": 0
},
    {
  "detailActor": "",
  "detailArea": "",
  "detailDesc": "class.movie_story3@text",
  "detailDirector": "",
  "detailImg": "",
  "detailNoteUrl": "",
  "detailRemark": "",
  "detailUi": "1",
  "detailYear": "",
  "discern": "",
  "enable": true,
  "enableFind": true,
  "exclude": "",
  "findActor": "",
  "findArea": "",
  "findDesc": "",
  "findDirector": "",
  "findImg": "",
  "findList": "",
  "findName": "",
  "findNoteUrl": "",
  "findRemark": "",
  "findUrl": "",
  "findYear": "",
  "httpUserAgent": "",
  "loginText": "",
  "loginUrl": "",
  "parserType": "4",
  "parserUrl": "",
  "play": "",
  "playHeader": "",
  "playList": "class.movurl@tag.li",
  "playName": "tag.a@text",
  "playUrl": "tag.a@href@js:result.replace('/play/','https://www.agefans.cc/play/')",
  "reqUrl": "",
  "searchActor": "tag.span.9@class.cell_imform_value@text",
  "searchArea": "tag.span.7@class.cell_imform_value@text",
  "searchDesc": "tag.div.0@class.cell_imform_desc@text",
  "searchDirector": "tag.span.5@class.cell_imform_value@text",
  "searchImg": "tag.a@img@src",
  "searchList": "class.baseblock@class.cell",
  "searchName": "tag.a@class.cell_imform_name@text",
  "searchNoteUrl": "tag.a.0@href",
  "searchRemark": "tag.a.0@style.newname@text",
  "searchUrl": "https://www.agefans.cc/search?query=searchKey&page=1",
  "searchYear": "tag.span@class.cell_imform_kv@text",
  "serialNumber": 6,
  "sortName": "",
  "sortNameList": "",
  "sortUrlList": "",
  "sourceGroup": "",
  "sourceName": "AGE动漫",
  "sourceUrl": "https://www.agefans.cc",
  "weight": 0
}
]
  }
}
